Workbook

Sheet Cover
A1: Cloud.AI SaaS Financial Model
A3: Model type | B3: 24-month B2B SaaS operating model
A4: Currency | B4: USD
A5: Forecast period | B5: May-2026 to Apr-2028
A6: Revenue model | B6: Monthly subscription SaaS
A7: Prepared for | B7: Founder / investor review
A8: Key logic | B8: Driver-based customer, MRR, ARR, COGS, opex, cash, and SaaS KPIs
A9: Model quality | B9: Inputs separated from formulas; key outputs summarized in dashboard
A10: Important note | B10: Demo model based on user-provided assumptions and clearly marked GPT assumptions
A12: Color Legend
A13: Blue font / yellow fill | B13: Hardcoded input or editable assumption
A14: Black font | B14: Formula calculation
A15: Green font | B15: Link from another sheet
A16: Red / amber flags | B16: Risk or warning area

Sheet Assumptions
A1: Cloud.AI Model Assumptions
A2: Input / Driver | B2: Unit | C2: Value | D2: Source | E2: Notes
A3: MODEL SETUP
A4: Company name | B4: text | C4: Cloud.AI | D4: User provided | E4: B2B SaaS company
A5: Forecast start month | B5: date | C5: 46143 | D5: Assumption | E5: Adjust if needed
A6: Forecast period | B6: months | C6: 24 | D6: User provided | E6: Monthly forecast
A7: Currency | B7: text | C7: USD | D7: User provided
A8: Starting cash | B8: $ | C8: 400000 | D8: User provided | E8: Opening cash balance
A9: Minimum cash threshold | B9: $ | C9: 75000 | D9: Assumption | E9: Used for funding need
A11: REVENUE DRIVERS
A12: Starting customers | B12: customers | C12: 50 | D12: User provided | E12: Opening customer count
A13: Starting MRR | B13: $ | C13: 25000 | D13: User provided | E13: Starting recurring revenue
A14: Starting ARPU | B14: $ / customer / month | C14: 500 | D14: User provided | E14: Must tie to starting MRR / customers
A15: ARPU consistency check | B15: text | C15: =IF(ROUND(C13/C12,0)=ROUND(C14,0),"OK","CHECK") -> OK | D15: Formula | E15: Starting MRR ÷ customers
A16: Month 1 new customers | B16: customers | C16: 8 | D16: User provided | E16: New customers in first forecast month
A17: New customer growth | B17: MoM % | C17: 0.05 | D17: User provided | E17: New customer adds grow monthly
A18: Monthly customer churn | B18: % | C18: 0.03 | D18: User provided | E18: Customer churn
A19: Monthly expansion / price uplift | B19: MoM % | C19: 0.005 | D19: Assumption | E19: Optional expansion logic
A20: Onboarding / services fee | B20: $ per new customer | C20: 0 | D20: Assumption | E20: Zero for pure monthly SaaS
A22: COGS / GROSS MARGIN
A23: Gross margin target | B23: % | C23: 0.78 | D23: User provided | E23: Target gross margin
A24: Hosting / cloud cost | B24: % revenue | C24: 0.08 | D24: Assumption | E24: Part of COGS
A25: Third-party software COGS | B25: % revenue | C25: 0.03 | D25: Assumption | E25: Part of COGS
A26: Payment processing | B26: % revenue | C26: 0.015 | D26: Assumption | E26: Part of COGS
A27: Customer support / implementation COGS | B27: balancing bucket | C27: Formula-driven | D27: GPT model logic | E27: Used in COGS sheet to reach gross margin target after specific COGS buckets
A29: HEADCOUNT ASSUMPTIONS
A30: Payroll tax and benefits | B30: % salary | C30: 0.15 | D30: Assumption | E30: Fully loaded cost assumption
A31: Annual salary inflation | B31: % | C31: 0.03 | D31: Assumption | E31: Applied every 12 months
A33: OPEX ASSUMPTIONS
A34: S&M base tools / events | B34: $ / month | C34: 5000 | D34: Assumption | E34: Non-payroll S&M
A35: Paid acquisition spend | B35: $ / new customer | C35: 1200 | D35: Assumption | E35: Variable CAC driver
A36: R&D tools baseline | B36: $ / month | C36: 4000 | D36: Assumption | E36: Non-payroll R&D
A37: G&A admin baseline | B37: $ / month | C37: 6000 | D37: Assumption | E37: Non-payroll G&A
A38: Non-payroll opex growth | B38: MoM % | C38: 0.01 | D38: Assumption | E38: Monthly escalation
A39: One-time legal/compliance month | B39: month # | C39: 12 | D39: Assumption | E39: Month number for one-time spend
A40: One-time legal/compliance spend | B40: $ | C40: 15000 | D40: Assumption | E40: One-time cost
A42: CASH ASSUMPTIONS
A43: Monthly cash collection rate | B43: % revenue | C43: 1 | D43: Assumption | E43: Monthly billing = 100% collection
A44: Monthly capex | B44: $ | C44: 0 | D44: Assumption | E44: Set if applicable
A45: Planned equity funding | B45: $ | C45: 0 | D45: Assumption | E45: Optional funding
A46: Funding month | B46: month # | C46: 0 | D46: Assumption | E46: 0 = none

Sheet Revenue Model
A1: Revenue Model
A2: Driver-based customer build, MRR, ARR, churn, expansion, and services revenue
A4: Line Item | B4: May-26 | C4: Jun-26 | D4: Jul-26 | E4: Aug-26 | F4: Sep-26 | G4: Oct-26 | H4: Nov-26 | I4: Dec-26 | J4: Jan-27 | K4: Feb-27 | L4: Mar-27 | M4: Apr-27 | N4: May-27 | O4: Jun-27 | P4: Jul-27 | Q4: Aug-27 | R4: Sep-27 | S4: Oct-27 | T4: Nov-27 | U4: Dec-27 | V4: Jan-28 | W4: Feb-28 | X4: Mar-28 | Y4: Apr-28
A5: Customer Build
A6: Opening Customers | B6: =Assumptions!$C$12 -> 50 | C6: ='Revenue Model'!B9 -> 56.5 | D6: ='Revenue Model'!C9 -> 63.205 | E6: ='Revenue Model'!D9 -> 70.12885 | F6: ='Revenue Model'!E9 -> 77.285984 | G6: ='Revenue Model'!F9 -> 84.691455 | H6: ='Revenue Model'!G9 -> 92.360964 | I6: ='Revenue Model'!H9 -> 100.3109 | J6: ='Revenue Model'!I9 -> 108.55838 | ... Y6: ='Revenue Model'!X9 -> 282.33705
A7: New Customers | B7: =Assumptions!$C$16 -> 8 | C7: ='Revenue Model'!B7*(1+Assumptions!$C$17) -> 8.4 | D7: ='Revenue Model'!C7*(1+Assumptions!$C$17) -> 8.82 | E7: ='Revenue Model'!D7*(1+Assumptions!$C$17) -> 9.261 | F7: ='Revenue Model'!E7*(1+Assumptions!$C$17) -> 9.72405 | G7: ='Revenue Model'!F7*(1+Assumptions!$C$17) -> 10.210253 | H7: ='Revenue Model'!G7*(1+Assumptions!$C$17) -> 10.720765 | I7: ='Revenue Model'!H7*(1+Assumptions!$C$17) -> 11.256803 | J7: ='Revenue Model'!I7*(1+Assumptions!$C$17) -> 11.819644 | ... Y7: ='Revenue Model'!X7*(1+Assumptions!$C$17) -> 24.57219
A8: Churned Customers | B8: =B6*Assumptions!$C$18 -> 1.5 | C8: =C6*Assumptions!$C$18 -> 1.695 | D8: =D6*Assumptions!$C$18 -> 1.89615 | E8: =E6*Assumptions!$C$18 -> 2.1038655 | F8: =F6*Assumptions!$C$18 -> 2.3185795 | G8: =G6*Assumptions!$C$18 -> 2.5407436 | H8: =H6*Assumptions!$C$18 -> 2.7708289 | I8: =I6*Assumptions!$C$18 -> 3.009327 | ... Y8: =Y6*Assumptions!$C$18 -> 8.4701116
A9: Ending Customers | B9: =B6+B7-B8 -> 56.5 | C9: =C6+C7-C8 -> 63.205 | D9: =D6+D7-D8 -> 70.12885 | E9: =E6+E7-E8 -> 77.285984 | F9: =F6+F7-F8 -> 84.691455 | G9: =G6+G7-G8 -> 92.360964 | H9: =H6+H7-H8 -> 100.3109 | I9: =I6+I7-I8 -> 108.55838 | ... Y9: =Y6+Y7-Y8 -> 298.43913
A10: Average Customers | B10: =AVERAGE(B6,B9) -> 53.25 | C10: =AVERAGE(C6,C9) -> 59.8525 | D10: =AVERAGE(D6,D9) -> 66.666925 | E10: =AVERAGE(E6,E9) -> 73.707417 | F10: =AVERAGE(F6,F9) -> 80.98872 | G10: =AVERAGE(G6,G9) -> 88.526209 | H10: =AVERAGE(H6,H9) -> 96.335932 | I10: =AVERAGE(I6,I9) -> 104.43464 | ... Y10: =AVERAGE(Y6,Y9) -> 290.38809
A12: MRR and Revenue Build
A13: Opening MRR | B13: =Assumptions!$C$13 -> 25000 | C13: ='Revenue Model'!B17 -> 28391.25 | D13: ='Revenue Model'!C17 -> 31898.21 | E13: ='Revenue Model'!D17 -> 35528.02 | F13: ='Revenue Model'!E17 -> 39288.143 | G13: ='Revenue Model'!F17 -> 43186.381 | H13: ='Revenue Model'!G17 -> 47230.896 | I13: ='Revenue Model'!H17 -> 51430.223 | J13: ='Revenue Model'!I17 -> 55793.297 | ... Y13: ='Revenue Model'!X17 -> 148444.9
A14: New MRR | B14: =B7*Assumptions!$C$14 -> 4000 | C14: =C7*Assumptions!$C$14 -> 4200 | D14: =D7*Assumptions!$C$14 -> 4410 | E14: =E7*Assumptions!$C$14 -> 4630.5 | F14: =F7*Assumptions!$C$14 -> 4862.025 | G14: =G7*Assumptions!$C$14 -> 5105.1263 | H14: =H7*Assumptions!$C$14 -> 5360.3826 | I14: =I7*Assumptions!$C$14 -> 5628.4017 | ... Y14: =Y7*Assumptions!$C$14 -> 12286.095
A15: Churned MRR | B15: =B13*Assumptions!$C$18 -> 750 | C15: =C13*Assumptions!$C$18 -> 851.7375 | D15: =D13*Assumptions!$C$18 -> 956.9463 | E15: =E13*Assumptions!$C$18 -> 1065.8406 | F15: =F13*Assumptions!$C$18 -> 1178.6443 | G15: =G13*Assumptions!$C$18 -> 1295.5914 | H15: =H13*Assumptions!$C$18 -> 1416.9269 | I15: =I13*Assumptions!$C$18 -> 1542.9067 | ... Y15: =Y13*Assumptions!$C$18 -> 4453.3469
A16: Expansion MRR | B16: =(B13-B15+B14)*Assumptions!$C$19 -> 141.25 | C16: =(C13-C15+C14)*Assumptions!$C$19 -> 158.69756 | D16: =(D13-D15+D14)*Assumptions!$C$19 -> 176.75632 | E16: =(E13-E15+E14)*Assumptions!$C$19 -> 195.4634 | F16: =(F13-F15+F14)*Assumptions!$C$19 -> 214.85762 | G16: =(G13-G15+G14)*Assumptions!$C$19 -> 234.97958 | H16: =(H13-H15+H14)*Assumptions!$C$19 -> 255.87176 | I16: =(I13-I15+I14)*Assumptions!$C$19 -> 277.57859 | ... Y16: =(Y13-Y15+Y14)*Assumptions!$C$19 -> 781.38823
A17: Ending MRR | B17: =B13+B14-B15+B16 -> 28391.25 | C17: =C13+C14-C15+C16 -> 31898.21 | D17: =D13+D14-D15+D16 -> 35528.02 | E17: =E13+E14-E15+E16 -> 39288.143 | F17: =F13+F14-F15+F16 -> 43186.381 | G17: =G13+G14-G15+G16 -> 47230.896 | H17: =H13+H14-H15+H16 -> 51430.223 | I17: =I13+I14-I15+I16 -> 55793.297 | ... Y17: =Y13+Y14-Y15+Y16 -> 157059.03
A18: ARR | B18: =B17*12 -> 340695 | C18: =C17*12 -> 382778.52 | D18: =D17*12 -> 426336.24 | E18: =E17*12 -> 471457.71 | F18: =F17*12 -> 518236.57 | G18: =G17*12 -> 566770.75 | H18: =H17*12 -> 617162.68 | I18: =I17*12 -> 669519.56 | ... Y18: =Y17*12 -> 1884708.4
A19: Recognized Subscription Revenue | B19: =AVERAGE(B13,B17) -> 26695.625 | C19: =AVERAGE(C13,C17) -> 30144.73 | D19: =AVERAGE(D13,D17) -> 33713.115 | E19: =AVERAGE(E13,E17) -> 37408.081 | F19: =AVERAGE(F13,F17) -> 41237.262 | G19: =AVERAGE(G13,G17) -> 45208.638 | H19: =AVERAGE(H13,H17) -> 49330.559 | I19: =AVERAGE(I13,I17) -> 53611.76 | ... Y19: =AVERAGE(Y13,Y17) -> 152751.97
A20: Onboarding / Services Revenue | B20: =B7*Assumptions!$C$20 -> 0 | C20: =C7*Assumptions!$C$20 -> 0 | D20: =D7*Assumptions!$C$20 -> 0 | E20: =E7*Assumptions!$C$20 -> 0 | F20: =F7*Assumptions!$C$20 -> 0 | G20: =G7*Assumptions!$C$20 -> 0 | H20: =H7*Assumptions!$C$20 -> 0 | I20: =I7*Assumptions!$C$20 -> 0 | ... Y20: =Y7*Assumptions!$C$20 -> 0
A21: Total Revenue | B21: =B19+B20 -> 26695.625 | C21: =C19+C20 -> 30144.73 | D21: =D19+D20 -> 33713.115 | E21: =E19+E20 -> 37408.081 | F21: =F19+F20 -> 41237.262 | G21: =G19+G20 -> 45208.638 | H21: =H19+H20 -> 49330.559 | I21: =I19+I20 -> 53611.76 | ... Y21: =Y19+Y20 -> 152751.97
A23: SaaS Metrics
A24: Customer Churn % | B24: =B8/B6 -> 0.03 | C24: =C8/C6 -> 0.03 | D24: =D8/D6 -> 0.03 | E24: =E8/E6 -> 0.03 | F24: =F8/F6 -> 0.03 | G24: =G8/G6 -> 0.03 | H24: =H8/H6 -> 0.03 | I24: =I8/I6 -> 0.03 | ... Y24: =Y8/Y6 -> 0.03
A25: MRR Growth % | B25: ="n/a" -> n/a | C25: =C17/B17-1 -> 0.12352257 | D25: =D17/C17-1 -> 0.11379353 | E25: =E17/D17-1 -> 0.10583542 | F25: =F17/E17-1 -> 0.099221751 | G25: =G17/F17-1 -> 0.093652542 | H25: =H17/G17-1 -> 0.088910604 | I25: =I17/H17-1 -> 0.084834818 | J25: =J17/I17-1 -> 0.081303127 | ... Y25: =Y17/X17-1 -> 0.058029184
A26: Net New MRR | B26: =B17-B13 -> 3391.25 | C26: =C17-C13 -> 3506.9601 | D26: =D17-D13 -> 3629.81 | E26: =E17-E13 -> 3760.1228 | F26: =F17-F13 -> 3898.2383 | G26: =G17-G13 -> 4044.5144 | H26: =H17-H13 -> 4199.3275 | I26: =I17-I13 -> 4363.0736 | ... Y26: =Y17-Y13 -> 8614.1363
A27: ARPU | B27: =B17/B9 -> 502.5 | C27: =C17/C9 -> 504.67859 | D27: =D17/D9 -> 506.61062 | E27: =E17/E9 -> 508.34758 | F27: =F17/F9 -> 509.92607 | G27: =G17/G9 -> 511.37292 | H27: =H17/H9 -> 512.70822 | I27: =I17/I9 -> 513.94741 | ... Y27: =Y17/Y9 -> 526.26823
A28: Net Revenue Retention % | B28: =(B13-B15+B16)/B13 -> 0.97565 | C28: =(C13-C15+C16)/C13 -> 0.97558966 | D28: =(D13-D15+D16)/D13 -> 0.97554126 | E28: =(E13-E15+E16)/E13 -> 0.97550167 | F28: =(F13-F15+F16)/F13 -> 0.97546876 | G28: =(G13-G15+G16)/G13 -> 0.97544106 | H28: =(H13-H15+H16)/H13 -> 0.97541747 | I28: =(I13-I15+I16)/I13 -> 0.97539719 | ... Y28: =(Y13-Y15+Y16)/Y13 -> 0.97526383

Sheet COGS
A1: COGS and Gross Margin
A2: COGS built from revenue-linked drivers and implementation support assumptions
A4: Line Item | B4: May-26 | C4: Jun-26 | D4: Jul-26 | E4: Aug-26 | F4: Sep-26 | G4: Oct-26 | H4: Nov-26 | I4: Dec-26 | J4: Jan-27 | K4: Feb-27 | L4: Mar-27 | M4: Apr-27 | N4: May-27 | O4: Jun-27 | P4: Jul-27 | Q4: Aug-27 | R4: Sep-27 | S4: Oct-27 | T4: Nov-27 | U4: Dec-27 | V4: Jan-28 | W4: Feb-28 | X4: Mar-28 | Y4: Apr-28
A5: COGS Build
A6: Subscription Revenue | B6: ='Revenue Model'!B21 -> 26695.625 | C6: ='Revenue Model'!C21 -> 30144.73 | D6: ='Revenue Model'!D21 -> 33713.115 | E6: ='Revenue Model'!E21 -> 37408.081 | F6: ='Revenue Model'!F21 -> 41237.262 | G6: ='Revenue Model'!G21 -> 45208.638 | H6: ='Revenue Model'!H21 -> 49330.559 | I6: ='Revenue Model'!I21 -> 53611.76 | ... Y6: ='Revenue Model'!Y21 -> 152751.97
A7: Hosting / Cloud COGS | B7: =B6*Assumptions!$C$24 -> 2135.65 | C7: =C6*Assumptions!$C$24 -> 2411.5784 | D7: =D6*Assumptions!$C$24 -> 2697.0492 | E7: =E6*Assumptions!$C$24 -> 2992.6465 | F7: =F6*Assumptions!$C$24 -> 3298.981 | G7: =G6*Assumptions!$C$24 -> 3616.6911 | H7: =H6*Assumptions!$C$24 -> 3946.4447 | I7: =I6*Assumptions!$C$24 -> 4288.9408 | ... Y7: =Y6*Assumptions!$C$24 -> 12220.157
A8: Third-party Software COGS | B8: =B6*Assumptions!$C$25 -> 800.86875 | C8: =C6*Assumptions!$C$25 -> 904.3419 | D8: =D6*Assumptions!$C$25 -> 1011.3935 | E8: =E6*Assumptions!$C$25 -> 1122.2424 | F8: =F6*Assumptions!$C$25 -> 1237.1179 | G8: =G6*Assumptions!$C$25 -> 1356.2592 | H8: =H6*Assumptions!$C$25 -> 1479.9168 | I8: =I6*Assumptions!$C$25 -> 1608.3528 | ... Y8: =Y6*Assumptions!$C$25 -> 4582.559
A9: Payment Processing | B9: =B6*Assumptions!$C$26 -> 400.43437 | C9: =C6*Assumptions!$C$26 -> 452.17095 | D9: =D6*Assumptions!$C$26 -> 505.69673 | E9: =E6*Assumptions!$C$26 -> 561.12122 | F9: =F6*Assumptions!$C$26 -> 618.55893 | G9: =G6*Assumptions!$C$26 -> 678.12958 | H9: =H6*Assumptions!$C$26 -> 739.95839 | I9: =I6*Assumptions!$C$26 -> 804.1764 | ... Y9: =Y6*Assumptions!$C$26 -> 2291.2795
A10: Customer Support / Implementation COGS | B10: =MAX(0,B6*(1-Assumptions!$C$23)-SUM(B7:B9)) -> 2536.0844 | C10: =MAX(0,C6*(1-Assumptions!$C$23)-SUM(C7:C9)) -> 2863.7494 | D10: =MAX(0,D6*(1-Assumptions!$C$23)-SUM(D7:D9)) -> 3202.7459 | E10: =MAX(0,E6*(1-Assumptions!$C$23)-SUM(E7:E9)) -> 3553.7677 | F10: =MAX(0,F6*(1-Assumptions!$C$23)-SUM(F7:F9)) -> 3917.5399 | G10: =MAX(0,G6*(1-Assumptions!$C$23)-SUM(G7:G9)) -> 4294.8206 | H10: =MAX(0,H6*(1-Assumptions!$C$23)-SUM(H7:H9)) -> 4686.4031 | I10: =MAX(0,I6*(1-Assumptions!$C$23)-SUM(I7:I9)) -> 5093.1172 | ... Y10: =MAX(0,Y6*(1-Assumptions!$C$23)-SUM(Y7:Y9)) -> 14511.437
A11: Total COGS | B11: =SUM(B7:B10) -> 5873.0375 | C11: =SUM(C7:C10) -> 6631.8406 | D11: =SUM(D7:D10) -> 7416.8853 | E11: =SUM(E7:E10) -> 8229.7779 | F11: =SUM(F7:F10) -> 9072.1976 | G11: =SUM(G7:G10) -> 9945.9004 | H11: =SUM(H7:H10) -> 10852.723 | I11: =SUM(I7:I10) -> 11794.587 | ... Y11: =SUM(Y7:Y10) -> 33605.433
A12: Gross Profit | B12: =B6-B11 -> 20822.588 | C12: =C6-C11 -> 23512.889 | D12: =D6-D11 -> 26296.23 | E12: =E6-E11 -> 29178.304 | F12: =F6-F11 -> 32165.064 | G12: =G6-G11 -> 35262.738 | H12: =H6-H11 -> 38477.836 | I12: =I6-I11 -> 41817.173 | ... Y12: =Y6-Y11 -> 119146.53
A13: Gross Margin % | B13: =B12/B6 -> 0.78 | C13: =C12/C6 -> 0.78 | D13: =D12/D6 -> 0.78 | E13: =E12/E6 -> 0.78 | F13: =F12/F6 -> 0.78 | G13: =G12/G6 -> 0.78 | H13: =H12/H6 -> 0.78 | I13: =I12/I6 -> 0.78 | ... Y13: =Y12/Y6 -> 0.78
A15: Target Check
A16: Target Gross Margin % | B16: =Assumptions!$C$23 -> 0.78 | C16: =Assumptions!$C$23 -> 0.78 | D16: =Assumptions!$C$23 -> 0.78 | E16: =Assumptions!$C$23 -> 0.78 | F16: =Assumptions!$C$23 -> 0.78 | G16: =Assumptions!$C$23 -> 0.78 | H16: =Assumptions!$C$23 -> 0.78 | I16: =Assumptions!$C$23 -> 0.78 | ... Y16: =Assumptions!$C$23 -> 0.78
A17: Variance vs Target | B17: =B13-B16 -> 0 | C17: =C13-C16 -> 0 | D17: =D13-D16 -> 0 | E17: =E13-E16 -> 0 | F17: =F13-F16 -> 0 | G17: =G13-G16 -> 0 | H17: =H13-H16 -> 0 | I17: =I13-I16 -> 0 | ... Y17: =Y13-Y16 -> 0

Sheet Headcount
A1: Headcount Plan
A2: Department-level team plan with salary and benefits assumptions
A3: Month # | B3: 1 | C3: 2 | D3: 3 | E3: 4 | F3: 5 | G3: 6 | H3: 7 | I3: 8 | J3: 9 | K3: 10 | L3: 11 | M3: 12 | N3: 13 | O3: 14 | P3: 15 | Q3: 16 | R3: 17 | S3: 18 | T3: 19 | U3: 20 | V3: 21 | W3: 22 | X3: 23 | Y3: 24
A4: Line Item | B4: May-26 | C4: Jun-26 | D4: Jul-26 | E4: Aug-26 | F4: Sep-26 | G4: Oct-26 | H4: Nov-26 | I4: Dec-26 | J4: Jan-27 | K4: Feb-27 | L4: Mar-27 | M4: Apr-27 | N4: May-27 | O4: Jun-27 | P4: Jul-27 | Q4: Aug-27 | R4: Sep-27 | S4: Oct-27 | T4: Nov-27 | U4: Dec-27 | V4: Jan-28 | W4: Feb-28 | X4: Mar-28 | Y4: Apr-28
A5: Headcount by Department
A6: Sales & Marketing HC | B6: =COUNTIFS($B$19:$B$25,"Sales & Marketing",$C$19:$C$25,"<="&B$3) -> 1 | C6: =COUNTIFS($B$19:$B$25,"Sales & Marketing",$C$19:$C$25,"<="&C$3) -> 1 | D6: =COUNTIFS($B$19:$B$25,"Sales & Marketing",$C$19:$C$25,"<="&D$3) -> 1 | E6: =COUNTIFS($B$19:$B$25,"Sales & Marketing",$C$19:$C$25,"<="&E$3) -> 2 | F6: =COUNTIFS($B$19:$B$25,"Sales & Marketing",$C$19:$C$25,"<="&F$3) -> 2 | G6: =COUNTIFS($B$19:$B$25,"Sales & Marketing",$C$19:$C$25,"<="&G$3) -> 2 | H6: =COUNTIFS($B$19:$B$25,"Sales & Marketing",$C$19:$C$25,"<="&H$3) -> 2 | I6: =COUNTIFS($B$19:$B$25,"Sales & Marketing",$C$19:$C$25,"<="&I$3) -> 2 | ... Y6: =COUNTIFS($B$19:$B$25,"Sales & Marketing",$C$19:$C$25,"<="&Y$3) -> 2
A7: R&D / Product HC | B7: =COUNTIFS($B$19:$B$25,"R&D / Product",$C$19:$C$25,"<="&B$3) -> 1 | C7: =COUNTIFS($B$19:$B$25,"R&D / Product",$C$19:$C$25,"<="&C$3) -> 1 | D7: =COUNTIFS($B$19:$B$25,"R&D / Product",$C$19:$C$25,"<="&D$3) -> 1 | E7: =COUNTIFS($B$19:$B$25,"R&D / Product",$C$19:$C$25,"<="&E$3) -> 1 | F7: =COUNTIFS($B$19:$B$25,"R&D / Product",$C$19:$C$25,"<="&F$3) -> 1 | G7: =COUNTIFS($B$19:$B$25,"R&D / Product",$C$19:$C$25,"<="&G$3) -> 2 | H7: =COUNTIFS($B$19:$B$25,"R&D / Product",$C$19:$C$25,"<="&H$3) -> 2 | I7: =COUNTIFS($B$19:$B$25,"R&D / Product",$C$19:$C$25,"<="&I$3) -> 3 | ... Y7: =COUNTIFS($B$19:$B$25,"R&D / Product",$C$19:$C$25,"<="&Y$3) -> 3
A8: G&A HC | B8: =COUNTIFS($B$19:$B$25,"G&A",$C$19:$C$25,"<="&B$3) -> 1 | C8: =COUNTIFS($B$19:$B$25,"G&A",$C$19:$C$25,"<="&C$3) -> 1 | D8: =COUNTIFS($B$19:$B$25,"G&A",$C$19:$C$25,"<="&D$3) -> 1 | E8: =COUNTIFS($B$19:$B$25,"G&A",$C$19:$C$25,"<="&E$3) -> 1 | F8: =COUNTIFS($B$19:$B$25,"G&A",$C$19:$C$25,"<="&F$3) -> 1 | G8: =COUNTIFS($B$19:$B$25,"G&A",$C$19:$C$25,"<="&G$3) -> 1 | H8: =COUNTIFS($B$19:$B$25,"G&A",$C$19:$C$25,"<="&H$3) -> 1 | I8: =COUNTIFS($B$19:$B$25,"G&A",$C$19:$C$25,"<="&I$3) -> 1 | ... Y8: =COUNTIFS($B$19:$B$25,"G&A",$C$19:$C$25,"<="&Y$3) -> 2
A9: Total Headcount | B9: =SUM(B6:B8) -> 3 | C9: =SUM(C6:C8) -> 3 | D9: =SUM(D6:D8) -> 3 | E9: =SUM(E6:E8) -> 4 | F9: =SUM(F6:F8) -> 4 | G9: =SUM(G6:G8) -> 5 | H9: =SUM(H6:H8) -> 5 | I9: =SUM(I6:I8) -> 6 | ... Y9: =SUM(Y6:Y8) -> 7
A11: Payroll Cost by Department
A12: Sales & Marketing Payroll | B12: =SUMIFS($D$19:$D$25,$B$19:$B$25,"Sales & Marketing",$C$19:$C$25,"<="&B$3)*(1+Assumptions!$C$30)*POWER(1+Assumptions!$C$31,INT((B$3-1)/12)) -> 9200 | C12: =SUMIFS($D$19:$D$25,$B$19:$B$25,"Sales & Marketing",$C$19:$C$25,"<="&C$3)*(1+Assumptions!$C$30)*POWER(1+Assumptions!$C$31,INT((C$3-1)/12)) -> 9200 | D12: =SUMIFS($D$19:$D$25,$B$19:$B$25,"Sales & Marketing",$C$19:$C$25,"<="&D$3)*(1+Assumptions!$C$30)*POWER(1+Assumptions!$C$31,INT((D$3-1)/12)) -> 9200 | E12: =SUMIFS($D$19:$D$25,$B$19:$B$25,"Sales & Marketing",$C$19:$C$25,"<="&E$3)*(1+Assumptions!$C$30)*POWER(1+Assumptions!$C$31,INT((E$3-1)/12)) -> 15525 | F12: =SUMIFS($D$19:$D$25,$B$19:$B$25,"Sales & Marketing",$C$19:$C$25,"<="&F$3)*(1+Assumptions!$C$30)*POWER(1+Assumptions!$C$31,INT((F$3-1)/12)) -> 15525 | G12: =SUMIFS($D$19:$D$25,$B$19:$B$25,"Sales & Marketing",$C$19:$C$25,"<="&G$3)*(1+Assumptions!$C$30)*POWER(1+Assumptions!$C$31,INT((G$3-1)/12)) -> 15525 | H12: =SUMIFS($D$19:$D$25,$B$19:$B$25,"Sales & Marketing",$C$19:$C$25,"<="&H$3)*(1+Assumptions!$C$30)*POWER(1+Assumptions!$C$31,INT((H$3-1)/12)) -> 15525 | I12: =SUMIFS($D$19:$D$25,$B$19:$B$25,"Sales & Marketing",$C$19:$C$25,"<="&I$3)*(1+Assumptions!$C$30)*POWER(1+Assumptions!$C$31,INT((I$3-1)/12)) -> 15525 | ... Y12: =SUMIFS($D$19:$D$25,$B$19:$B$25,"Sales & Marketing",$C$19:$C$25,"<="&Y$3)*(1+Assumptions!$C$30)*POWER(1+Assumptions!$C$31,INT((Y$3-1)/12)) -> 15990.75
A13: R&D / Product Payroll | B13: =SUMIFS($D$19:$D$25,$B$19:$B$25,"R&D / Product",$C$19:$C$25,"<="&B$3)*(1+Assumptions!$C$30)*POWER(1+Assumptions!$C$31,INT((B$3-1)/12)) -> 10350 | C13: =SUMIFS($D$19:$D$25,$B$19:$B$25,"R&D / Product",$C$19:$C$25,"<="&C$3)*(1+Assumptions!$C$30)*POWER(1+Assumptions!$C$31,INT((C$3-1)/12)) -> 10350 | D13: =SUMIFS($D$19:$D$25,$B$19:$B$25,"R&D / Product",$C$19:$C$25,"<="&D$3)*(1+Assumptions!$C$30)*POWER(1+Assumptions!$C$31,INT((D$3-1)/12)) -> 10350 | E13: =SUMIFS($D$19:$D$25,$B$19:$B$25,"R&D / Product",$C$19:$C$25,"<="&E$3)*(1+Assumptions!$C$30)*POWER(1+Assumptions!$C$31,INT((E$3-1)/12)) -> 10350 | F13: =SUMIFS($D$19:$D$25,$B$19:$B$25,"R&D / Product",$C$19:$C$25,"<="&F$3)*(1+Assumptions!$C$30)*POWER(1+Assumptions!$C$31,INT((F$3-1)/12)) -> 10350 | G13: =SUMIFS($D$19:$D$25,$B$19:$B$25,"R&D / Product",$C$19:$C$25,"<="&G$3)*(1+Assumptions!$C$30)*POWER(1+Assumptions!$C$31,INT((G$3-1)/12)) -> 20700 | H13: =SUMIFS($D$19:$D$25,$B$19:$B$25,"R&D / Product",$C$19:$C$25,"<="&H$3)*(1+Assumptions!$C$30)*POWER(1+Assumptions!$C$31,INT((H$3-1)/12)) -> 20700 | I13: =SUMIFS($D$19:$D$25,$B$19:$B$25,"R&D / Product",$C$19:$C$25,"<="&I$3)*(1+Assumptions!$C$30)*POWER(1+Assumptions!$C$31,INT((I$3-1)/12)) -> 28750 | ... Y13: =SUMIFS($D$19:$D$25,$B$19:$B$25,"R&D / Product",$C$19:$C$25,"<="&Y$3)*(1+Assumptions!$C$30)*POWER(1+Assumptions!$C$31,INT((Y$3-1)/12)) -> 29612.5
A14: G&A Payroll | B14: =SUMIFS($D$19:$D$25,$B$19:$B$25,"G&A",$C$19:$C$25,"<="&B$3)*(1+Assumptions!$C$30)*POWER(1+Assumptions!$C$31,INT((B$3-1)/12)) -> 7475 | C14: =SUMIFS($D$19:$D$25,$B$19:$B$25,"G&A",$C$19:$C$25,"<="&C$3)*(1+Assumptions!$C$30)*POWER(1+Assumptions!$C$31,INT((C$3-1)/12)) -> 7475 | D14: =SUMIFS($D$19:$D$25,$B$19:$B$25,"G&A",$C$19:$C$25,"<="&D$3)*(1+Assumptions!$C$30)*POWER(1+Assumptions!$C$31,INT((D$3-1)/12)) -> 7475 | E14: =SUMIFS($D$19:$D$25,$B$19:$B$25,"G&A",$C$19:$C$25,"<="&E$3)*(1+Assumptions!$C$30)*POWER(1+Assumptions!$C$31,INT((E$3-1)/12)) -> 7475 | F14: =SUMIFS($D$19:$D$25,$B$19:$B$25,"G&A",$C$19:$C$25,"<="&F$3)*(1+Assumptions!$C$30)*POWER(1+Assumptions!$C$31,INT((F$3-1)/12)) -> 7475 | G14: =SUMIFS($D$19:$D$25,$B$19:$B$25,"G&A",$C$19:$C$25,"<="&G$3)*(1+Assumptions!$C$30)*POWER(1+Assumptions!$C$31,INT((G$3-1)/12)) -> 7475 | H14: =SUMIFS($D$19:$D$25,$B$19:$B$25,"G&A",$C$19:$C$25,"<="&H$3)*(1+Assumptions!$C$30)*POWER(1+Assumptions!$C$31,INT((H$3-1)/12)) -> 7475 | I14: =SUMIFS($D$19:$D$25,$B$19:$B$25,"G&A",$C$19:$C$25,"<="&I$3)*(1+Assumptions!$C$30)*POWER(1+Assumptions!$C$31,INT((I$3-1)/12)) -> 7475 | ... Y14: =SUMIFS($D$19:$D$25,$B$19:$B$25,"G&A",$C$19:$C$25,"<="&Y$3)*(1+Assumptions!$C$30)*POWER(1+Assumptions!$C$31,INT((Y$3-1)/12)) -> 13029.5
A15: Total Payroll | B15: =SUM(B12:B14) -> 27025 | C15: =SUM(C12:C14) -> 27025 | D15: =SUM(D12:D14) -> 27025 | E15: =SUM(E12:E14) -> 33350 | F15: =SUM(F12:F14) -> 33350 | G15: =SUM(G12:G14) -> 43700 | H15: =SUM(H12:H14) -> 43700 | I15: =SUM(I12:I14) -> 51750 | ... Y15: =SUM(Y12:Y14) -> 58632.75
A17: Role Plan Reference
A18: Role | B18: Department | C18: Start Month | D18: Monthly Salary | E18: Notes
A19: AE / Growth Lead | B19: Sales & Marketing | C19: 1 | D19: 8000 | E19: GTM owner
A20: Customer Success Manager | B20: Sales & Marketing | C20: 4 | D20: 5500 | E20: Retention / onboarding
A21: Product Engineer 1 | B21: R&D / Product | C21: 1 | D21: 9000 | E21: Core product
A22: Product Engineer 2 | B22: R&D / Product | C22: 6 | D22: 9000 | E22: Scale support
A23: Product Designer | B23: R&D / Product | C23: 8 | D23: 7000 | E23: Product UX
A24: Finance & Ops Manager | B24: G&A | C24: 1 | D24: 6500 | E24: Ops / finance
A25: Admin / People Ops | B25: G&A | C25: 10 | D25: 4500 | E25: Admin support

Sheet Opex
A1: Operating Expenses
A2: Payroll and non-payroll operating expenses by department
A4: Line Item | B4: May-26 | C4: Jun-26 | D4: Jul-26 | E4: Aug-26 | F4: Sep-26 | G4: Oct-26 | H4: Nov-26 | I4: Dec-26 | J4: Jan-27 | K4: Feb-27 | L4: Mar-27 | M4: Apr-27 | N4: May-27 | O4: Jun-27 | P4: Jul-27 | Q4: Aug-27 | R4: Sep-27 | S4: Oct-27 | T4: Nov-27 | U4: Dec-27 | V4: Jan-28 | W4: Feb-28 | X4: Mar-28 | Y4: Apr-28
A5: Sales & Marketing
A6: S&M Payroll | B6: =Headcount!B12 -> 9200 | C6: =Headcount!C12 -> 9200 | D6: =Headcount!D12 -> 9200 | E6: =Headcount!E12 -> 15525 | F6: =Headcount!F12 -> 15525 | G6: =Headcount!G12 -> 15525 | H6: =Headcount!H12 -> 15525 | I6: =Headcount!I12 -> 15525 | ... Y6: =Headcount!Y12 -> 15990.75
A7: S&M Base Tools / Events | B7: =Assumptions!$C$34*POWER(1+Assumptions!$C$38,1-1) -> 5000 | C7: =Assumptions!$C$34*POWER(1+Assumptions!$C$38,2-1) -> 5050 | D7: =Assumptions!$C$34*POWER(1+Assumptions!$C$38,3-1) -> 5100.5 | E7: =Assumptions!$C$34*POWER(1+Assumptions!$C$38,4-1) -> 5151.505 | F7: =Assumptions!$C$34*POWER(1+Assumptions!$C$38,5-1) -> 5203.0201 | G7: =Assumptions!$C$34*POWER(1+Assumptions!$C$38,6-1) -> 5255.0503 | H7: =Assumptions!$C$34*POWER(1+Assumptions!$C$38,7-1) -> 5307.6008 | I7: =Assumptions!$C$34*POWER(1+Assumptions!$C$38,8-1) -> 5360.6768 | J7: =Assumptions!$C$34*POWER(1+Assumptions!$C$38,9-1) -> 5414.2835 | K7: =Assumptions!$C$34*POWER(1+Assumptions!$C$38,10-1) -> 5468.4264 | L7: =Assumptions!$C$34*POWER(1+Assumptions!$C$38,11-1) -> 5523.1106 | M7: =Assumptions!$C$34*POWER(1+Assumptions!$C$38,12-1) -> 5578.3417 | N7: =Assumptions!$C$34*POWER(1+Assumptions!$C$38,13-1) -> 5634.1252 | O7: =Assumptions!$C$34*POWER(1+Assumptions!$C$38,14-1) -> 5690.4664 | P7: =Assumptions!$C$34*POWER(1+Assumptions!$C$38,15-1) -> 5747.3711 | Q7: =Assumptions!$C$34*POWER(1+Assumptions!$C$38,16-1) -> 5804.8448 | R7: =Assumptions!$C$34*POWER(1+Assumptions!$C$38,17-1) -> 5862.8932 | S7: =Assumptions!$C$34*POWER(1+Assumptions!$C$38,18-1) -> 5921.5222 | T7: =Assumptions!$C$34*POWER(1+Assumptions!$C$38,19-1) -> 5980.7374 | U7: =Assumptions!$C$34*POWER(1+Assumptions!$C$38,20-1) -> 6040.5448 | V7: =Assumptions!$C$34*POWER(1+Assumptions!$C$38,21-1) -> 6100.9502 | W7: =Assumptions!$C$34*POWER(1+Assumptions!$C$38,22-1) -> 6161.9597 | X7: =Assumptions!$C$34*POWER(1+Assumptions!$C$38,23-1) -> 6223.5793 | Y7: =Assumptions!$C$34*POWER(1+Assumptions!$C$38,24-1) -> 6285.8151
A8: Paid Acquisition Spend | B8: ='Revenue Model'!B7*Assumptions!$C$35 -> 9600 | C8: ='Revenue Model'!C7*Assumptions!$C$35 -> 10080 | D8: ='Revenue Model'!D7*Assumptions!$C$35 -> 10584 | E8: ='Revenue Model'!E7*Assumptions!$C$35 -> 11113.2 | F8: ='Revenue Model'!F7*Assumptions!$C$35 -> 11668.86 | G8: ='Revenue Model'!G7*Assumptions!$C$35 -> 12252.303 | H8: ='Revenue Model'!H7*Assumptions!$C$35 -> 12864.918 | I8: ='Revenue Model'!I7*Assumptions!$C$35 -> 13508.164 | ... Y8: ='Revenue Model'!Y7*Assumptions!$C$35 -> 29486.628
A9: Total Sales & Marketing | B9: =SUM(B6:B8) -> 23800 | C9: =SUM(C6:C8) -> 24330 | D9: =SUM(D6:D8) -> 24884.5 | E9: =SUM(E6:E8) -> 31789.705 | F9: =SUM(F6:F8) -> 32396.88 | G9: =SUM(G6:G8) -> 33032.353 | H9: =SUM(H6:H8) -> 33697.519 | I9: =SUM(I6:I8) -> 34393.841 | ... Y9: =SUM(Y6:Y8) -> 51763.193
A11: R&D / Product
A12: R&D Payroll | B12: =Headcount!B13 -> 10350 | C12: =Headcount!C13 -> 10350 | D12: =Headcount!D13 -> 10350 | E12: =Headcount!E13 -> 10350 | F12: =Headcount!F13 -> 10350 | G12: =Headcount!G13 -> 20700 | H12: =Headcount!H13 -> 20700 | I12: =Headcount!I13 -> 28750 | ... Y12: =Headcount!Y13 -> 29612.5
A13: R&D Tools | B13: =Assumptions!$C$36*POWER(1+Assumptions!$C$38,1-1) -> 4000 | C13: =Assumptions!$C$36*POWER(1+Assumptions!$C$38,2-1) -> 4040 | D13: =Assumptions!$C$36*POWER(1+Assumptions!$C$38,3-1) -> 4080.4 | E13: =Assumptions!$C$36*POWER(1+Assumptions!$C$38,4-1) -> 4121.204 | F13: =Assumptions!$C$36*POWER(1+Assumptions!$C$38,5-1) -> 4162.416 | G13: =Assumptions!$C$36*POWER(1+Assumptions!$C$38,6-1) -> 4204.0402 | H13: =Assumptions!$C$36*POWER(1+Assumptions!$C$38,7-1) -> 4246.0806 | I13: =Assumptions!$C$36*POWER(1+Assumptions!$C$38,8-1) -> 4288.5414 | J13: =Assumptions!$C$36*POWER(1+Assumptions!$C$38,9-1) -> 4331.4268 | K13: =Assumptions!$C$36*POWER(1+Assumptions!$C$38,10-1) -> 4374.7411 | L13: =Assumptions!$C$36*POWER(1+Assumptions!$C$38,11-1) -> 4418.4885 | M13: =Assumptions!$C$36*POWER(1+Assumptions!$C$38,12-1) -> 4462.6734 | N13: =Assumptions!$C$36*POWER(1+Assumptions!$C$38,13-1) -> 4507.3001 | O13: =Assumptions!$C$36*POWER(1+Assumptions!$C$38,14-1) -> 4552.3731 | P13: =Assumptions!$C$36*POWER(1+Assumptions!$C$38,15-1) -> 4597.8969 | Q13: =Assumptions!$C$36*POWER(1+Assumptions!$C$38,16-1) -> 4643.8758 | R13: =Assumptions!$C$36*POWER(1+Assumptions!$C$38,17-1) -> 4690.3146 | S13: =Assumptions!$C$36*POWER(1+Assumptions!$C$38,18-1) -> 4737.2177 | T13: =Assumptions!$C$36*POWER(1+Assumptions!$C$38,19-1) -> 4784.5899 | U13: =Assumptions!$C$36*POWER(1+Assumptions!$C$38,20-1) -> 4832.4358 | V13: =Assumptions!$C$36*POWER(1+Assumptions!$C$38,21-1) -> 4880.7602 | W13: =Assumptions!$C$36*POWER(1+Assumptions!$C$38,22-1) -> 4929.5678 | X13: =Assumptions!$C$36*POWER(1+Assumptions!$C$38,23-1) -> 4978.8634 | Y13: =Assumptions!$C$36*POWER(1+Assumptions!$C$38,24-1) -> 5028.6521
A14: Total R&D | B14: =SUM(B12:B13) -> 14350 | C14: =SUM(C12:C13) -> 14390 | D14: =SUM(D12:D13) -> 14430.4 | E14: =SUM(E12:E13) -> 14471.204 | F14: =SUM(F12:F13) -> 14512.416 | G14: =SUM(G12:G13) -> 24904.04 | H14: =SUM(H12:H13) -> 24946.081 | I14: =SUM(I12:I13) -> 33038.541 | ... Y14: =SUM(Y12:Y13) -> 34641.152
A16: G&A
A17: G&A Payroll | B17: =Headcount!B14 -> 7475 | C17: =Headcount!C14 -> 7475 | D17: =Headcount!D14 -> 7475 | E17: =Headcount!E14 -> 7475 | F17: =Headcount!F14 -> 7475 | G17: =Headcount!G14 -> 7475 | H17: =Headcount!H14 -> 7475 | I17: =Headcount!I14 -> 7475 | ... Y17: =Headcount!Y14 -> 13029.5
A18: G&A Admin | B18: =Assumptions!$C$37*POWER(1+Assumptions!$C$38,1-1) -> 6000 | C18: =Assumptions!$C$37*POWER(1+Assumptions!$C$38,2-1) -> 6060 | D18: =Assumptions!$C$37*POWER(1+Assumptions!$C$38,3-1) -> 6120.6 | E18: =Assumptions!$C$37*POWER(1+Assumptions!$C$38,4-1) -> 6181.806 | F18: =Assumptions!$C$37*POWER(1+Assumptions!$C$38,5-1) -> 6243.6241 | G18: =Assumptions!$C$37*POWER(1+Assumptions!$C$38,6-1) -> 6306.0603 | H18: =Assumptions!$C$37*POWER(1+Assumptions!$C$38,7-1) -> 6369.1209 | I18: =Assumptions!$C$37*POWER(1+Assumptions!$C$38,8-1) -> 6432.8121 | J18: =Assumptions!$C$37*POWER(1+Assumptions!$C$38,9-1) -> 6497.1402 | K18: =Assumptions!$C$37*POWER(1+Assumptions!$C$38,10-1) -> 6562.1116 | L18: =Assumptions!$C$37*POWER(1+Assumptions!$C$38,11-1) -> 6627.7328 | M18: =Assumptions!$C$37*POWER(1+Assumptions!$C$38,12-1) -> 6694.0101 | N18: =Assumptions!$C$37*POWER(1+Assumptions!$C$38,13-1) -> 6760.9502 | O18: =Assumptions!$C$37*POWER(1+Assumptions!$C$38,14-1) -> 6828.5597 | P18: =Assumptions!$C$37*POWER(1+Assumptions!$C$38,15-1) -> 6896.8453 | Q18: =Assumptions!$C$37*POWER(1+Assumptions!$C$38,16-1) -> 6965.8137 | R18: =Assumptions!$C$37*POWER(1+Assumptions!$C$38,17-1) -> 7035.4719 | S18: =Assumptions!$C$37*POWER(1+Assumptions!$C$38,18-1) -> 7105.8266 | T18: =Assumptions!$C$37*POWER(1+Assumptions!$C$38,19-1) -> 7176.8849 | U18: =Assumptions!$C$37*POWER(1+Assumptions!$C$38,20-1) -> 7248.6537 | V18: =Assumptions!$C$37*POWER(1+Assumptions!$C$38,21-1) -> 7321.1402 | W18: =Assumptions!$C$37*POWER(1+Assumptions!$C$38,22-1) -> 7394.3516 | X18: =Assumptions!$C$37*POWER(1+Assumptions!$C$38,23-1) -> 7468.2952 | Y18: =Assumptions!$C$37*POWER(1+Assumptions!$C$38,24-1) -> 7542.9781
A19: One-time Legal / Compliance | B19: =IF(1=Assumptions!$C$39,Assumptions!$C$40,0) -> 0 | C19: =IF(2=Assumptions!$C$39,Assumptions!$C$40,0) -> 0 | D19: =IF(3=Assumptions!$C$39,Assumptions!$C$40,0) -> 0 | E19: =IF(4=Assumptions!$C$39,Assumptions!$C$40,0) -> 0 | F19: =IF(5=Assumptions!$C$39,Assumptions!$C$40,0) -> 0 | G19: =IF(6=Assumptions!$C$39,Assumptions!$C$40,0) -> 0 | H19: =IF(7=Assumptions!$C$39,Assumptions!$C$40,0) -> 0 | I19: =IF(8=Assumptions!$C$39,Assumptions!$C$40,0) -> 0 | J19: =IF(9=Assumptions!$C$39,Assumptions!$C$40,0) -> 0 | K19: =IF(10=Assumptions!$C$39,Assumptions!$C$40,0) -> 0 | L19: =IF(11=Assumptions!$C$39,Assumptions!$C$40,0) -> 0 | M19: =IF(12=Assumptions!$C$39,Assumptions!$C$40,0) -> 15000 | N19: =IF(13=Assumptions!$C$39,Assumptions!$C$40,0) -> 0 | O19: =IF(14=Assumptions!$C$39,Assumptions!$C$40,0) -> 0 | P19: =IF(15=Assumptions!$C$39,Assumptions!$C$40,0) -> 0 | Q19: =IF(16=Assumptions!$C$39,Assumptions!$C$40,0) -> 0 | R19: =IF(17=Assumptions!$C$39,Assumptions!$C$40,0) -> 0 | S19: =IF(18=Assumptions!$C$39,Assumptions!$C$40,0) -> 0 | T19: =IF(19=Assumptions!$C$39,Assumptions!$C$40,0) -> 0 | U19: =IF(20=Assumptions!$C$39,Assumptions!$C$40,0) -> 0 | V19: =IF(21=Assumptions!$C$39,Assumptions!$C$40,0) -> 0 | W19: =IF(22=Assumptions!$C$39,Assumptions!$C$40,0) -> 0 | X19: =IF(23=Assumptions!$C$39,Assumptions!$C$40,0) -> 0 | Y19: =IF(24=Assumptions!$C$39,Assumptions!$C$40,0) -> 0
A20: Total G&A | B20: =SUM(B17:B19) -> 13475 | C20: =SUM(C17:C19) -> 13535 | D20: =SUM(D17:D19) -> 13595.6 | E20: =SUM(E17:E19) -> 13656.806 | F20: =SUM(F17:F19) -> 13718.624 | G20: =SUM(G17:G19) -> 13781.06 | H20: =SUM(H17:H19) -> 13844.121 | I20: =SUM(I17:I19) -> 13907.812 | ... Y20: =SUM(Y17:Y19) -> 20572.478
A22: Total Opex | B22: =B9+B14+B20 -> 51625 | C22: =C9+C14+C20 -> 52255 | D22: =D9+D14+D20 -> 52910.5 | E22: =E9+E14+E20 -> 59917.715 | F22: =F9+F14+F20 -> 60627.92 | G22: =G9+G14+G20 -> 71717.454 | H22: =H9+H14+H20 -> 72487.72 | I22: =I9+I14+I20 -> 81340.194 | ... Y22: =Y9+Y14+Y20 -> 106976.82
A23: Total Payroll | B23: =B6+B12+B17 -> 27025 | C23: =C6+C12+C17 -> 27025 | D23: =D6+D12+D17 -> 27025 | E23: =E6+E12+E17 -> 33350 | F23: =F6+F12+F17 -> 33350 | G23: =G6+G12+G17 -> 43700 | H23: =H6+H12+H17 -> 43700 | I23: =I6+I12+I17 -> 51750 | ... Y23: =Y6+Y12+Y17 -> 58632.75
A24: Total Non-Payroll Opex | B24: =B22-B23 -> 24600 | C24: =C22-C23 -> 25230 | D24: =D22-D23 -> 25885.5 | E24: =E22-E23 -> 26567.715 | F24: =F22-F23 -> 27277.92 | G24: =G22-G23 -> 28017.454 | H24: =H22-H23 -> 28787.72 | I24: =I22-I23 -> 29590.194 | ... Y24: =Y22-Y23 -> 48344.073

Sheet P&L
A1: P&L Forecast
A2: Monthly P&L forecast with revenue, gross profit, EBITDA, and margin analysis
A4: Line Item | B4: May-26 | C4: Jun-26 | D4: Jul-26 | E4: Aug-26 | F4: Sep-26 | G4: Oct-26 | H4: Nov-26 | I4: Dec-26 | J4: Jan-27 | K4: Feb-27 | L4: Mar-27 | M4: Apr-27 | N4: May-27 | O4: Jun-27 | P4: Jul-27 | Q4: Aug-27 | R4: Sep-27 | S4: Oct-27 | T4: Nov-27 | U4: Dec-27 | V4: Jan-28 | W4: Feb-28 | X4: Mar-28 | Y4: Apr-28
A5: Revenue
A6: Subscription Revenue | B6: ='Revenue Model'!B19 -> 26695.625 | C6: ='Revenue Model'!C19 -> 30144.73 | D6: ='Revenue Model'!D19 -> 33713.115 | E6: ='Revenue Model'!E19 -> 37408.081 | F6: ='Revenue Model'!F19 -> 41237.262 | G6: ='Revenue Model'!G19 -> 45208.638 | H6: ='Revenue Model'!H19 -> 49330.559 | I6: ='Revenue Model'!I19 -> 53611.76 | ... Y6: ='Revenue Model'!Y19 -> 152751.97
A7: Onboarding / Services Revenue | B7: ='Revenue Model'!B20 -> 0 | C7: ='Revenue Model'!C20 -> 0 | D7: ='Revenue Model'!D20 -> 0 | E7: ='Revenue Model'!E20 -> 0 | F7: ='Revenue Model'!F20 -> 0 | G7: ='Revenue Model'!G20 -> 0 | H7: ='Revenue Model'!H20 -> 0 | I7: ='Revenue Model'!I20 -> 0 | ... Y7: ='Revenue Model'!Y20 -> 0
A8: Total Revenue | B8: =SUM(B6:B7) -> 26695.625 | C8: =SUM(C6:C7) -> 30144.73 | D8: =SUM(D6:D7) -> 33713.115 | E8: =SUM(E6:E7) -> 37408.081 | F8: =SUM(F6:F7) -> 41237.262 | G8: =SUM(G6:G7) -> 45208.638 | H8: =SUM(H6:H7) -> 49330.559 | I8: =SUM(I6:I7) -> 53611.76 | ... Y8: =SUM(Y6:Y7) -> 152751.97
A10: COGS
A11: Total COGS | B11: =COGS!B11 -> 5873.0375 | C11: =COGS!C11 -> 6631.8406 | D11: =COGS!D11 -> 7416.8853 | E11: =COGS!E11 -> 8229.7779 | F11: =COGS!F11 -> 9072.1976 | G11: =COGS!G11 -> 9945.9004 | H11: =COGS!H11 -> 10852.723 | I11: =COGS!I11 -> 11794.587 | ... Y11: =COGS!Y11 -> 33605.433
A12: Gross Profit | B12: =B8-B11 -> 20822.588 | C12: =C8-C11 -> 23512.889 | D12: =D8-D11 -> 26296.23 | E12: =E8-E11 -> 29178.304 | F12: =F8-F11 -> 32165.064 | G12: =G8-G11 -> 35262.738 | H12: =H8-H11 -> 38477.836 | I12: =I8-I11 -> 41817.173 | ... Y12: =Y8-Y11 -> 119146.53
A13: Gross Margin % | B13: =B12/B8 -> 0.78 | C13: =C12/C8 -> 0.78 | D13: =D12/D8 -> 0.78 | E13: =E12/E8 -> 0.78 | F13: =F12/F8 -> 0.78 | G13: =G12/G8 -> 0.78 | H13: =H12/H8 -> 0.78 | I13: =I12/I8 -> 0.78 | ... Y13: =Y12/Y8 -> 0.78
A15: Operating Expenses
A16: Sales & Marketing | B16: =Opex!B9 -> 23800 | C16: =Opex!C9 -> 24330 | D16: =Opex!D9 -> 24884.5 | E16: =Opex!E9 -> 31789.705 | F16: =Opex!F9 -> 32396.88 | G16: =Opex!G9 -> 33032.353 | H16: =Opex!H9 -> 33697.519 | I16: =Opex!I9 -> 34393.841 | ... Y16: =Opex!Y9 -> 51763.193
A17: R&D / Product | B17: =Opex!B14 -> 14350 | C17: =Opex!C14 -> 14390 | D17: =Opex!D14 -> 14430.4 | E17: =Opex!E14 -> 14471.204 | F17: =Opex!F14 -> 14512.416 | G17: =Opex!G14 -> 24904.04 | H17: =Opex!H14 -> 24946.081 | I17: =Opex!I14 -> 33038.541 | ... Y17: =Opex!Y14 -> 34641.152
A18: G&A | B18: =Opex!B20 -> 13475 | C18: =Opex!C20 -> 13535 | D18: =Opex!D20 -> 13595.6 | E18: =Opex!E20 -> 13656.806 | F18: =Opex!F20 -> 13718.624 | G18: =Opex!G20 -> 13781.06 | H18: =Opex!H20 -> 13844.121 | I18: =Opex!I20 -> 13907.812 | ... Y18: =Opex!Y20 -> 20572.478
A19: Total Opex | B19: =SUM(B16:B18) -> 51625 | C19: =SUM(C16:C18) -> 52255 | D19: =SUM(D16:D18) -> 52910.5 | E19: =SUM(E16:E18) -> 59917.715 | F19: =SUM(F16:F18) -> 60627.92 | G19: =SUM(G16:G18) -> 71717.454 | H19: =SUM(H16:H18) -> 72487.72 | I19: =SUM(I16:I18) -> 81340.194 | ... Y19: =SUM(Y16:Y18) -> 106976.82
A21: Profitability
A22: EBITDA | B22: =B12-B19 -> -30802.412 | C22: =C12-C19 -> -28742.111 | D22: =D12-D19 -> -26614.27 | E22: =E12-E19 -> -30739.411 | F22: =F12-F19 -> -28462.856 | G22: =G12-G19 -> -36454.716 | H22: =H12-H19 -> -34009.884 | I22: =I12-I19 -> -39523.022 | ... Y22: =Y12-Y19 -> 12169.71
A23: EBITDA Margin % | B23: =B22/B8 -> -1.1538375 | C23: =C22/C8 -> -0.95347049 | D23: =D22/D8 -> -0.78943373 | E23: =E22/E8 -> -0.82173184 | F23: =F22/F8 -> -0.69022176 | G23: =G22/G8 -> -0.80636615 | H23: =H22/H8 -> -0.68942831 | I23: =I22/I8 -> -0.73720806 | ... Y23: =Y22/Y8 -> 0.079669747

Sheet Cash Runway
A1: Cash Runway
A2: Cash flow, burn, runway, and funding need
A4: Line Item | B4: May-26 | C4: Jun-26 | D4: Jul-26 | E4: Aug-26 | F4: Sep-26 | G4: Oct-26 | H4: Nov-26 | I4: Dec-26 | J4: Jan-27 | K4: Feb-27 | L4: Mar-27 | M4: Apr-27 | N4: May-27 | O4: Jun-27 | P4: Jul-27 | Q4: Aug-27 | R4: Sep-27 | S4: Oct-27 | T4: Nov-27 | U4: Dec-27 | V4: Jan-28 | W4: Feb-28 | X4: Mar-28 | Y4: Apr-28
A5: Cash Flow
A6: Opening Cash | B6: =Assumptions!$C$8 -> 400000 | C6: ='Cash Runway'!B19 -> 369197.59 | D6: ='Cash Runway'!C19 -> 340455.48 | E6: ='Cash Runway'!D19 -> 313841.21 | F6: ='Cash Runway'!E19 -> 283101.8 | G6: ='Cash Runway'!F19 -> 254638.94 | H6: ='Cash Runway'!G19 -> 218184.22 | I6: ='Cash Runway'!H19 -> 184174.34 | J6: ='Cash Runway'!I19 -> 144651.32 | ... Y6: ='Cash Runway'!X19 -> -167869.99
A7: Cash Collections | B7: ='Revenue Model'!B21*Assumptions!$C$43 -> 26695.625 | C7: ='Revenue Model'!C21*Assumptions!$C$43 -> 30144.73 | D7: ='Revenue Model'!D21*Assumptions!$C$43 -> 33713.115 | E7: ='Revenue Model'!E21*Assumptions!$C$43 -> 37408.081 | F7: ='Revenue Model'!F21*Assumptions!$C$43 -> 41237.262 | G7: ='Revenue Model'!G21*Assumptions!$C$43 -> 45208.638 | H7: ='Revenue Model'!H21*Assumptions!$C$43 -> 49330.559 | I7: ='Revenue Model'!I21*Assumptions!$C$43 -> 53611.76 | ... Y7: ='Revenue Model'!Y21*Assumptions!$C$43 -> 152751.97
A8: Planned Equity Funding | B8: =IF(1=Assumptions!$C$46,Assumptions!$C$45,0) -> 0 | C8: =IF(2=Assumptions!$C$46,Assumptions!$C$45,0) -> 0 | D8: =IF(3=Assumptions!$C$46,Assumptions!$C$45,0) -> 0 | E8: =IF(4=Assumptions!$C$46,Assumptions!$C$45,0) -> 0 | F8: =IF(5=Assumptions!$C$46,Assumptions!$C$45,0) -> 0 | G8: =IF(6=Assumptions!$C$46,Assumptions!$C$45,0) -> 0 | H8: =IF(7=Assumptions!$C$46,Assumptions!$C$45,0) -> 0 | I8: =IF(8=Assumptions!$C$46,Assumptions!$C$45,0) -> 0 | J8: =IF(9=Assumptions!$C$46,Assumptions!$C$45,0) -> 0 | K8: =IF(10=Assumptions!$C$46,Assumptions!$C$45,0) -> 0 | L8: =IF(11=Assumptions!$C$46,Assumptions!$C$45,0) -> 0 | M8: =IF(12=Assumptions!$C$46,Assumptions!$C$45,0) -> 0 | N8: =IF(13=Assumptions!$C$46,Assumptions!$C$45,0) -> 0 | O8: =IF(14=Assumptions!$C$46,Assumptions!$C$45,0) -> 0 | P8: =IF(15=Assumptions!$C$46,Assumptions!$C$45,0) -> 0 | Q8: =IF(16=Assumptions!$C$46,Assumptions!$C$45,0) -> 0 | R8: =IF(17=Assumptions!$C$46,Assumptions!$C$45,0) -> 0 | S8: =IF(18=Assumptions!$C$46,Assumptions!$C$45,0) -> 0 | T8: =IF(19=Assumptions!$C$46,Assumptions!$C$45,0) -> 0 | U8: =IF(20=Assumptions!$C$46,Assumptions!$C$45,0) -> 0 | V8: =IF(21=Assumptions!$C$46,Assumptions!$C$45,0) -> 0 | W8: =IF(22=Assumptions!$C$46,Assumptions!$C$45,0) -> 0 | X8: =IF(23=Assumptions!$C$46,Assumptions!$C$45,0) -> 0 | Y8: =IF(24=Assumptions!$C$46,Assumptions!$C$45,0) -> 0
A9: Total Cash Inflows | B9: =SUM(B7:B8) -> 26695.625 | C9: =SUM(C7:C8) -> 30144.73 | D9: =SUM(D7:D8) -> 33713.115 | E9: =SUM(E7:E8) -> 37408.081 | F9: =SUM(F7:F8) -> 41237.262 | G9: =SUM(G7:G8) -> 45208.638 | H9: =SUM(H7:H8) -> 49330.559 | I9: =SUM(I7:I8) -> 53611.76 | ... Y9: =SUM(Y7:Y8) -> 152751.97
A11: Cash Outflows
A12: COGS Cash Outflow | B12: =COGS!B11 -> 5873.0375 | C12: =COGS!C11 -> 6631.8406 | D12: =COGS!D11 -> 7416.8853 | E12: =COGS!E11 -> 8229.7779 | F12: =COGS!F11 -> 9072.1976 | G12: =COGS!G11 -> 9945.9004 | H12: =COGS!H11 -> 10852.723 | I12: =COGS!I11 -> 11794.587 | ... Y12: =COGS!Y11 -> 33605.433
A13: Opex Cash Outflow | B13: =Opex!B22 -> 51625 | C13: =Opex!C22 -> 52255 | D13: =Opex!D22 -> 52910.5 | E13: =Opex!E22 -> 59917.715 | F13: =Opex!F22 -> 60627.92 | G13: =Opex!G22 -> 71717.454 | H13: =Opex!H22 -> 72487.72 | I13: =Opex!I22 -> 81340.194 | ... Y13: =Opex!Y22 -> 106976.82
A14: Capex | B14: =Assumptions!$C$44 -> 0 | C14: =Assumptions!$C$44 -> 0 | D14: =Assumptions!$C$44 -> 0 | E14: =Assumptions!$C$44 -> 0 | F14: =Assumptions!$C$44 -> 0 | G14: =Assumptions!$C$44 -> 0 | H14: =Assumptions!$C$44 -> 0 | I14: =Assumptions!$C$44 -> 0 | ... Y14: =Assumptions!$C$44 -> 0
A15: Total Cash Outflows | B15: =SUM(B12:B14) -> 57498.037 | C15: =SUM(C12:C14) -> 58886.841 | D15: =SUM(D12:D14) -> 60327.385 | E15: =SUM(E12:E14) -> 68147.493 | F15: =SUM(F12:F14) -> 69700.118 | G15: =SUM(G12:G14) -> 81663.354 | H15: =SUM(H12:H14) -> 83340.443 | I15: =SUM(I12:I14) -> 93134.782 | ... Y15: =SUM(Y12:Y14) -> 140582.26
A17: Burn and Runway
A18: Net Burn | B18: =B15-B9 -> 30802.412 | C18: =C15-C9 -> 28742.111 | D18: =D15-D9 -> 26614.27 | E18: =E15-E9 -> 30739.411 | F18: =F15-F9 -> 28462.856 | G18: =G15-G9 -> 36454.716 | H18: =H15-H9 -> 34009.884 | I18: =I15-I9 -> 39523.022 | ... Y18: =Y15-Y9 -> -12169.71
A19: Ending Cash | B19: =B6+B9-B15 -> 369197.59 | C19: =C6+C9-C15 -> 340455.48 | D19: =D6+D9-D15 -> 313841.21 | E19: =E6+E9-E15 -> 283101.8 | F19: =F6+F9-F15 -> 254638.94 | G19: =G6+G9-G15 -> 218184.22 | H19: =H6+H9-H15 -> 184174.34 | I19: =I6+I9-I15 -> 144651.32 | ... Y19: =Y6+Y9-Y15 -> -155700.28
A20: Runway (months) | B20: =IF(B18>0,B19/B18,"Profitable") -> 11.985996 | C20: =IF(C18>0,C19/C18,"Profitable") -> 11.84518 | D20: =IF(D18>0,D19/D18,"Profitable") -> 11.792215 | E20: =IF(E18>0,E19/E18,"Profitable") -> 9.2097338 | F20: =IF(F18>0,F19/F18,"Profitable") -> 8.9463595 | G20: =IF(G18>0,G19/G18,"Profitable") -> 5.9850754 | H20: =IF(H18>0,H19/H18,"Profitable") -> 5.4153181 | I20: =IF(I18>0,I19/I18,"Profitable") -> 3.6599256 | ... Y20: =IF(Y18>0,Y19/Y18,"Profitable") -> Profitable
A21: Funding Need to Minimum Cash | B21: =MAX(0,Assumptions!$C$9-B19) -> 0 | C21: =MAX(0,Assumptions!$C$9-C19) -> 0 | D21: =MAX(0,Assumptions!$C$9-D19) -> 0 | E21: =MAX(0,Assumptions!$C$9-E19) -> 0 | F21: =MAX(0,Assumptions!$C$9-F19) -> 0 | G21: =MAX(0,Assumptions!$C$9-G19) -> 0 | H21: =MAX(0,Assumptions!$C$9-H19) -> 0 | I21: =MAX(0,Assumptions!$C$9-I19) -> 0 | ... Y21: =MAX(0,Assumptions!$C$9-Y19) -> 230700.28
A22: Cash Status | B22: =IF(B19<0,"Negative Cash",IF(B19<Assumptions!$C$9,"Below Minimum","Healthy")) -> Healthy | C22: =IF(C19<0,"Negative Cash",IF(C19<Assumptions!$C$9,"Below Minimum","Healthy")) -> Healthy | D22: =IF(D19<0,"Negative Cash",IF(D19<Assumptions!$C$9,"Below Minimum","Healthy")) -> Healthy | E22: =IF(E19<0,"Negative Cash",IF(E19<Assumptions!$C$9,"Below Minimum","Healthy")) -> Healthy | F22: =IF(F19<0,"Negative Cash",IF(F19<Assumptions!$C$9,"Below Minimum","Healthy")) -> Healthy | G22: =IF(G19<0,"Negative Cash",IF(G19<Assumptions!$C$9,"Below Minimum","Healthy")) -> Healthy | H22: =IF(H19<0,"Negative Cash",IF(H19<Assumptions!$C$9,"Below Minimum","Healthy")) -> Healthy | I22: =IF(I19<0,"Negative Cash",IF(I19<Assumptions!$C$9,"Below Minimum","Healthy")) -> Healthy | ... Y22: =IF(Y19<0,"Negative Cash",IF(Y19<Assumptions!$C$9,"Below Minimum","Healthy")) -> Negative Cash

Sheet SaaS KPI Dashboard
A1: Cloud.AI SaaS KPI Dashboard
A2: Founder-friendly view of growth, profitability, runway, and SaaS metrics
A4: Ending ARR | D4: Ending MRR | G4: Ending Customers | J4: Ending Cash
A5: ='Revenue Model'!Y18 -> 1884708.4 | D5: ='Revenue Model'!Y17 -> 157059.03 | G5: ='Revenue Model'!Y9 -> 298.43913 | J5: ='Cash Runway'!Y19 -> -155700.28
A6: Annualized recurring revenue | D6: Monthly recurring revenue | G6: Customer count | J6: Liquidity position
A9: Gross Margin | D9: EBITDA Margin | G9: LTV:CAC | J9: Funding Need
A10: ='P&L'!Y13 -> 0.78 | D10: ='P&L'!Y23 -> 0.079669747 | G10: =IFERROR((Assumptions!$C$14*'P&L'!Y13/Assumptions!$C$18)/(Assumptions!$C$35),0) -> 10.833333 | J10: =MAX('Cash Runway'!B21:Y21) -> 252491.52
A11: Quality of revenue | D11: Operating profitability | G11: Unit economics | J11: Cash needed to keep minimum balance
A14: Plain-English Takeaways
A15: Growth | B15: ="ARR grows from "&TEXT('Revenue Model'!B18,"$#,##0")&" to "&TEXT('Revenue Model'!Y18,"$#,##0")&" over 24 months." -> ARR grows from $340,695 to $1,884,708 over 24 months.
A16: Margin | B16: ="Gross margin ends at "&TEXT('P&L'!Y13,"0.0%")&", compared with the target of "&TEXT(Assumptions!$C$23,"0.0%")&"." -> Gross margin ends at 78.0%, compared with the target of 78.0%.
A17: Cash | B17: ="Ending cash is "&TEXT('Cash Runway'!Y19,"$#,##0;($#,##0)")&". Maximum funding need is "&TEXT(MAX('Cash Runway'!B21:Y21),"$#,##0")&"." -> Ending cash is ($155,700). Maximum funding need is $252,492.
A18: Action | B18: Review hiring pace, CAC spend, pricing/expansion, and financing timing before investor use.
A21: Month | B21: MRR | C21: ARR | D21: Revenue | E21: Total Expenses | F21: Ending Cash
A22: ='Revenue Model'!B$4 -> May-26 | B22: ='Revenue Model'!B$17 -> 28391.25 | C22: ='Revenue Model'!B$18 -> 340695 | D22: ='P&L'!B$8 -> 26695.625 | E22: =COGS!B$11+Opex!B$22 -> 57498.037 | F22: ='Cash Runway'!B$19 -> 369197.59
A23: ='Revenue Model'!C$4 -> Jun-26 | B23: ='Revenue Model'!C$17 -> 31898.21 | C23: ='Revenue Model'!C$18 -> 382778.52 | D23: ='P&L'!C$8 -> 30144.73 | E23: =COGS!C$11+Opex!C$22 -> 58886.841 | F23: ='Cash Runway'!C$19 -> 340455.48
A24: ='Revenue Model'!D$4 -> Jul-26 | B24: ='Revenue Model'!D$17 -> 35528.02 | C24: ='Revenue Model'!D$18 -> 426336.24 | D24: ='P&L'!D$8 -> 33713.115 | E24: =COGS!D$11+Opex!D$22 -> 60327.385 | F24: ='Cash Runway'!D$19 -> 313841.21
A25: ='Revenue Model'!E$4 -> Aug-26 | B25: ='Revenue Model'!E$17 -> 39288.143 | C25: ='Revenue Model'!E$18 -> 471457.71 | D25: ='P&L'!E$8 -> 37408.081 | E25: =COGS!E$11+Opex!E$22 -> 68147.493 | F25: ='Cash Runway'!E$19 -> 283101.8
A26: ='Revenue Model'!F$4 -> Sep-26 | B26: ='Revenue Model'!F$17 -> 43186.381 | C26: ='Revenue Model'!F$18 -> 518236.57 | D26: ='P&L'!F$8 -> 41237.262 | E26: =COGS!F$11+Opex!F$22 -> 69700.118 | F26: ='Cash Runway'!F$19 -> 254638.94
A27: ='Revenue Model'!G$4 -> Oct-26 | B27: ='Revenue Model'!G$17 -> 47230.896 | C27: ='Revenue Model'!G$18 -> 566770.75 | D27: ='P&L'!G$8 -> 45208.638 | E27: =COGS!G$11+Opex!G$22 -> 81663.354 | F27: ='Cash Runway'!G$19 -> 218184.22
A28: ='Revenue Model'!H$4 -> Nov-26 | B28: ='Revenue Model'!H$17 -> 51430.223 | C28: ='Revenue Model'!H$18 -> 617162.68 | D28: ='P&L'!H$8 -> 49330.559 | E28: =COGS!H$11+Opex!H$22 -> 83340.443 | F28: ='Cash Runway'!H$19 -> 184174.34
A29: ='Revenue Model'!I$4 -> Dec-26 | B29: ='Revenue Model'!I$17 -> 55793.297 | C29: ='Revenue Model'!I$18 -> 669519.56 | D29: ='P&L'!I$8 -> 53611.76 | E29: =COGS!I$11+Opex!I$22 -> 93134.782 | F29: ='Cash Runway'!I$19 -> 144651.32
A30: ='Revenue Model'!J$4 -> Jan-27 | B30: ='Revenue Model'!J$17 -> 60329.466 | C30: ='Revenue Model'!J$18 -> 723953.59 | D30: ='P&L'!J$8 -> 58061.381 | E30: =COGS!J$11+Opex!J$22 -> 94949.927 | F30: ='Cash Runway'!J$19 -> 107762.77
A31: ='Revenue Model'!K$4 -> Feb-27 | B31: ='Revenue Model'!K$17 -> 65048.519 | C31: ='Revenue Model'!K$18 -> 780582.23 | D31: ='P&L'!K$8 -> 62688.993 | E31: =COGS!K$11+Opex!K$22 -> 102014.61 | F31: ='Cash Runway'!K$19 -> 68437.157
A32: ='Revenue Model'!L$4 -> Mar-27 | B32: ='Revenue Model'!L$17 -> 69960.706 | C32: ='Revenue Model'!L$18 -> 839528.47 | D32: ='P&L'!L$8 -> 67504.613 | E32: =COGS!L$11+Opex!L$22 -> 103982.74 | F32: ='Cash Runway'!L$19 -> 31959.034
A33: ='Revenue Model'!M$4 -> Apr-27 | B33: ='Revenue Model'!M$17 -> 75076.758 | C33: ='Revenue Model'!M$18 -> 900921.1 | D33: ='P&L'!M$8 -> 72518.732 | E33: =COGS!M$11+Opex!M$22 -> 121033.4 | F33: ='Cash Runway'!M$19 -> -16555.638
A34: ='Revenue Model'!N$4 -> May-27 | B34: ='Revenue Model'!N$17 -> 80407.92 | C34: ='Revenue Model'!N$18 -> 964895.04 | D34: ='P&L'!N$8 -> 77742.339 | E34: =COGS!N$11+Opex!N$22 -> 109878.66 | F34: ='Cash Runway'!N$19 -> -48691.96
A35: ='Revenue Model'!O$4 -> Jun-27 | B35: ='Revenue Model'!O$17 -> 85965.97 | C35: ='Revenue Model'!O$18 -> 1031591.6 | D35: ='P&L'!O$8 -> 83186.945 | E35: =COGS!O$11+Opex!O$22 -> 112107.51 | F35: ='Cash Runway'!O$19 -> -77612.523
A36: ='Revenue Model'!P$4 -> Jul-27 | B36: ='Revenue Model'!P$17 -> 91763.251 | C36: ='Revenue Model'!P$18 -> 1101159 | D36: ='P&L'!P$8 -> 88864.611 | E36: =COGS!P$11+Opex!P$22 -> 114432.42 | F36: ='Cash Runway'!P$19 -> -103180.33
A37: ='Revenue Model'!Q$4 -> Aug-27 | B37: ='Revenue Model'!Q$17 -> 97812.697 | C37: ='Revenue Model'!Q$18 -> 1173752.4 | D37: ='P&L'!Q$8 -> 94787.974 | E37: =COGS!Q$11+Opex!Q$22 -> 116858.35 | F37: ='Cash Runway'!Q$19 -> -125250.71
A38: ='Revenue Model'!R$4 -> Sep-27 | B38: ='Revenue Model'!R$17 -> 104127.86 | C38: ='Revenue Model'!R$18 -> 1249534.4 | D38: ='P&L'!R$8 -> 100970.28 | E38: =COGS!R$11+Opex!R$22 -> 119390.49 | F38: ='Cash Runway'!R$19 -> -143670.92
A39: ='Revenue Model'!S$4 -> Oct-27 | B39: ='Revenue Model'!S$17 -> 110722.96 | C39: ='Revenue Model'!S$18 -> 1328675.5 | D39: ='P&L'!S$8 -> 107425.41 | E39: =COGS!S$11+Opex!S$22 -> 122034.28 | F39: ='Cash Runway'!S$19 -> -158279.79
A40: ='Revenue Model'!T$4 -> Nov-27 | B40: ='Revenue Model'!T$17 -> 117612.89 | C40: ='Revenue Model'!T$18 -> 1411354.7 | D40: ='P&L'!T$8 -> 114167.92 | E40: =COGS!T$11+Opex!T$22 -> 124795.45 | F40: ='Cash Runway'!T$19 -> -168907.31
A41: ='Revenue Model'!U$4 -> Dec-27 | B41: ='Revenue Model'!U$17 -> 124813.26 | C41: ='Revenue Model'!U$18 -> 1497759.2 | D41: ='P&L'!U$8 -> 121213.08 | E41: =COGS!U$11+Opex!U$22 -> 127679.98 | F41: ='Cash Runway'!U$19 -> -175374.22
A42: ='Revenue Model'!V$4 -> Jan-28 | B42: ='Revenue Model'!V$17 -> 132340.47 | C42: ='Revenue Model'!V$18 -> 1588085.6 | D42: ='P&L'!V$8 -> 128576.87 | E42: =COGS!V$11+Opex!V$22 -> 130694.17 | F42: ='Cash Runway'!V$19 -> -177491.52
A43: ='Revenue Model'!W$4 -> Feb-28 | B43: ='Revenue Model'!W$17 -> 140211.67 | C43: ='Revenue Model'!W$18 -> 1682540.1 | D43: ='P&L'!W$8 -> 136276.07 | E43: =COGS!W$11+Opex!W$22 -> 133844.61 | F43: ='Cash Runway'!W$19 -> -175060.06
A44: ='Revenue Model'!X$4 -> Mar-28 | B44: ='Revenue Model'!X$17 -> 148444.9 | C44: ='Revenue Model'!X$18 -> 1781338.8 | D44: ='P&L'!X$8 -> 144328.29 | E44: =COGS!X$11+Opex!X$22 -> 137138.21 | F44: ='Cash Runway'!X$19 -> -167869.99
A45: ='Revenue Model'!Y$4 -> Apr-28 | B45: ='Revenue Model'!Y$17 -> 157059.03 | C45: ='Revenue Model'!Y$18 -> 1884708.4 | D45: ='P&L'!Y$8 -> 152751.97 | E45: =COGS!Y$11+Opex!Y$22 -> 140582.26 | F45: ='Cash Runway'!Y$19 -> -155700.28

Sheet Scenario Analysis
A1: Scenario Analysis
A3: Scenario | B3: New Customer Growth | C3: Monthly Churn | D3: ARPU Uplift | E3: Ending ARR | F3: Ending Cash | G3: Funding Need | H3: Comment
A4: Conservative | B4: 0.02 | C4: 0.04 | D4: 0.002 | E4: ='Revenue Model'!Y18*(1+(B4-Assumptions!$C$17)*8-(C4-Assumptions!$C$18)*10+(D4-Assumptions!$C$19)*6) -> 1209982.8 | F4: ='Cash Runway'!Y19+(E4-'Revenue Model'!Y18)*0.3 -> -358117.96 | G4: =MAX(0,Assumptions!$C$9-F4) -> 433117.96 | H4: Slower acquisition, higher churn
A5: Base Case | B5: 0.05 | C5: 0.03 | D5: 0.005 | E5: ='Revenue Model'!Y18*(1+(B5-Assumptions!$C$17)*8-(C5-Assumptions!$C$18)*10+(D5-Assumptions!$C$19)*6) -> 1884708.4 | F5: ='Cash Runway'!Y19+(E5-'Revenue Model'!Y18)*0.3 -> -155700.28 | G5: =MAX(0,Assumptions!$C$9-F5) -> 230700.28 | H5: Matches core model
A6: Optimistic | B6: 0.08 | C6: 0.02 | D6: 0.008 | E6: ='Revenue Model'!Y18*(1+(B6-Assumptions!$C$17)*8-(C6-Assumptions!$C$18)*10+(D6-Assumptions!$C$19)*6) -> 2559434 | F6: ='Cash Runway'!Y19+(E6-'Revenue Model'!Y18)*0.3 -> 46717.409 | G6: =MAX(0,Assumptions!$C$9-F6) -> 28282.591 | H6: Faster acquisition, lower churn

Sheet Charts
A1: Charts
A2: Clean chart sheet with helper data on the left and large charts on the right to avoid overlapping labels
A4: Month | B4: MRR | C4: ARR | D4: Revenue | F4: Month | G4: Revenue | H4: Total Expenses | J4: Month | K4: Ending Cash | M4: Month | N4: Ending Customers
A5: ='Revenue Model'!B$4 -> May-26 | B5: ='Revenue Model'!B$17 -> 28391.25 | C5: ='Revenue Model'!B$18 -> 340695 | D5: ='P&L'!B$8 -> 26695.625 | F5: ='P&L'!B$4 -> May-26 | G5: ='P&L'!B$8 -> 26695.625 | H5: =COGS!B$11+Opex!B$22 -> 57498.037 | J5: ='Cash Runway'!B$4 -> May-26 | K5: ='Cash Runway'!B$19 -> 369197.59 | M5: ='Revenue Model'!B$4 -> May-26 | N5: ='Revenue Model'!B$9 -> 56.5
A6: ='Revenue Model'!C$4 -> Jun-26 | B6: ='Revenue Model'!C$17 -> 31898.21 | C6: ='Revenue Model'!C$18 -> 382778.52 | D6: ='P&L'!C$8 -> 30144.73 | F6: ='P&L'!C$4 -> Jun-26 | G6: ='P&L'!C$8 -> 30144.73 | H6: =COGS!C$11+Opex!C$22 -> 58886.841 | J6: ='Cash Runway'!C$4 -> Jun-26 | K6: ='Cash Runway'!C$19 -> 340455.48 | M6: ='Revenue Model'!C$4 -> Jun-26 | N6: ='Revenue Model'!C$9 -> 63.205
A7: ='Revenue Model'!D$4 -> Jul-26 | B7: ='Revenue Model'!D$17 -> 35528.02 | C7: ='Revenue Model'!D$18 -> 426336.24 | D7: ='P&L'!D$8 -> 33713.115 | F7: ='P&L'!D$4 -> Jul-26 | G7: ='P&L'!D$8 -> 33713.115 | H7: =COGS!D$11+Opex!D$22 -> 60327.385 | J7: ='Cash Runway'!D$4 -> Jul-26 | K7: ='Cash Runway'!D$19 -> 313841.21 | M7: ='Revenue Model'!D$4 -> Jul-26 | N7: ='Revenue Model'!D$9 -> 70.12885
A8: ='Revenue Model'!E$4 -> Aug-26 | B8: ='Revenue Model'!E$17 -> 39288.143 | C8: ='Revenue Model'!E$18 -> 471457.71 | D8: ='P&L'!E$8 -> 37408.081 | F8: ='P&L'!E$4 -> Aug-26 | G8: ='P&L'!E$8 -> 37408.081 | H8: =COGS!E$11+Opex!E$22 -> 68147.493 | J8: ='Cash Runway'!E$4 -> Aug-26 | K8: ='Cash Runway'!E$19 -> 283101.8 | M8: ='Revenue Model'!E$4 -> Aug-26 | N8: ='Revenue Model'!E$9 -> 77.285984
A9: ='Revenue Model'!F$4 -> Sep-26 | B9: ='Revenue Model'!F$17 -> 43186.381 | C9: ='Revenue Model'!F$18 -> 518236.57 | D9: ='P&L'!F$8 -> 41237.262 | F9: ='P&L'!F$4 -> Sep-26 | G9: ='P&L'!F$8 -> 41237.262 | H9: =COGS!F$11+Opex!F$22 -> 69700.118 | J9: ='Cash Runway'!F$4 -> Sep-26 | K9: ='Cash Runway'!F$19 -> 254638.94 | M9: ='Revenue Model'!F$4 -> Sep-26 | N9: ='Revenue Model'!F$9 -> 84.691455
A10: ='Revenue Model'!G$4 -> Oct-26 | B10: ='Revenue Model'!G$17 -> 47230.896 | C10: ='Revenue Model'!G$18 -> 566770.75 | D10: ='P&L'!G$8 -> 45208.638 | F10: ='P&L'!G$4 -> Oct-26 | G10: ='P&L'!G$8 -> 45208.638 | H10: =COGS!G$11+Opex!G$22 -> 81663.354 | J10: ='Cash Runway'!G$4 -> Oct-26 | K10: ='Cash Runway'!G$19 -> 218184.22 | M10: ='Revenue Model'!G$4 -> Oct-26 | N10: ='Revenue Model'!G$9 -> 92.360964
A11: ='Revenue Model'!H$4 -> Nov-26 | B11: ='Revenue Model'!H$17 -> 51430.223 | C11: ='Revenue Model'!H$18 -> 617162.68 | D11: ='P&L'!H$8 -> 49330.559 | F11: ='P&L'!H$4 -> Nov-26 | G11: ='P&L'!H$8 -> 49330.559 | H11: =COGS!H$11+Opex!H$22 -> 83340.443 | J11: ='Cash Runway'!H$4 -> Nov-26 | K11: ='Cash Runway'!H$19 -> 184174.34 | M11: ='Revenue Model'!H$4 -> Nov-26 | N11: ='Revenue Model'!H$9 -> 100.3109
A12: ='Revenue Model'!I$4 -> Dec-26 | B12: ='Revenue Model'!I$17 -> 55793.297 | C12: ='Revenue Model'!I$18 -> 669519.56 | D12: ='P&L'!I$8 -> 53611.76 | F12: ='P&L'!I$4 -> Dec-26 | G12: ='P&L'!I$8 -> 53611.76 | H12: =COGS!I$11+Opex!I$22 -> 93134.782 | J12: ='Cash Runway'!I$4 -> Dec-26 | K12: ='Cash Runway'!I$19 -> 144651.32 | M12: ='Revenue Model'!I$4 -> Dec-26 | N12: ='Revenue Model'!I$9 -> 108.55838
A13: ='Revenue Model'!J$4 -> Jan-27 | B13: ='Revenue Model'!J$17 -> 60329.466 | C13: ='Revenue Model'!J$18 -> 723953.59 | D13: ='P&L'!J$8 -> 58061.381 | F13: ='P&L'!J$4 -> Jan-27 | G13: ='P&L'!J$8 -> 58061.381 | H13: =COGS!J$11+Opex!J$22 -> 94949.927 | J13: ='Cash Runway'!J$4 -> Jan-27 | K13: ='Cash Runway'!J$19 -> 107762.77 | M13: ='Revenue Model'!J$4 -> Jan-27 | N13: ='Revenue Model'!J$9 -> 117.12127
A14: ='Revenue Model'!K$4 -> Feb-27 | B14: ='Revenue Model'!K$17 -> 65048.519 | C14: ='Revenue Model'!K$18 -> 780582.23 | D14: ='P&L'!K$8 -> 62688.993 | F14: ='P&L'!K$4 -> Feb-27 | G14: ='P&L'!K$8 -> 62688.993 | H14: =COGS!K$11+Opex!K$22 -> 102014.61 | J14: ='Cash Runway'!K$4 -> Feb-27 | K14: ='Cash Runway'!K$19 -> 68437.157 | M14: ='Revenue Model'!K$4 -> Feb-27 | N14: ='Revenue Model'!K$9 -> 126.01826
A15: ='Revenue Model'!L$4 -> Mar-27 | B15: ='Revenue Model'!L$17 -> 69960.706 | C15: ='Revenue Model'!L$18 -> 839528.47 | D15: ='P&L'!L$8 -> 67504.613 | F15: ='P&L'!L$4 -> Mar-27 | G15: ='P&L'!L$8 -> 67504.613 | H15: =COGS!L$11+Opex!L$22 -> 103982.74 | J15: ='Cash Runway'!L$4 -> Mar-27 | K15: ='Cash Runway'!L$19 -> 31959.034 | M15: ='Revenue Model'!L$4 -> Mar-27 | N15: ='Revenue Model'!L$9 -> 135.26887
A16: ='Revenue Model'!M$4 -> Apr-27 | B16: ='Revenue Model'!M$17 -> 75076.758 | C16: ='Revenue Model'!M$18 -> 900921.1 | D16: ='P&L'!M$8 -> 72518.732 | F16: ='P&L'!M$4 -> Apr-27 | G16: ='P&L'!M$8 -> 72518.732 | H16: =COGS!M$11+Opex!M$22 -> 121033.4 | J16: ='Cash Runway'!M$4 -> Apr-27 | K16: ='Cash Runway'!M$19 -> -16555.638 | M16: ='Revenue Model'!M$4 -> Apr-27 | N16: ='Revenue Model'!M$9 -> 144.89351
A17: ='Revenue Model'!N$4 -> May-27 | B17: ='Revenue Model'!N$17 -> 80407.92 | C17: ='Revenue Model'!N$18 -> 964895.04 | D17: ='P&L'!N$8 -> 77742.339 | F17: ='P&L'!N$4 -> May-27 | G17: ='P&L'!N$8 -> 77742.339 | H17: =COGS!N$11+Opex!N$22 -> 109878.66 | J17: ='Cash Runway'!N$4 -> May-27 | K17: ='Cash Runway'!N$19 -> -48691.96 | M17: ='Revenue Model'!N$4 -> May-27 | N17: ='Revenue Model'!N$9 -> 154.91356
A18: ='Revenue Model'!O$4 -> Jun-27 | B18: ='Revenue Model'!O$17 -> 85965.97 | C18: ='Revenue Model'!O$18 -> 1031591.6 | D18: ='P&L'!O$8 -> 83186.945 | F18: ='P&L'!O$4 -> Jun-27 | G18: ='P&L'!O$8 -> 83186.945 | H18: =COGS!O$11+Opex!O$22 -> 112107.51 | J18: ='Cash Runway'!O$4 -> Jun-27 | K18: ='Cash Runway'!O$19 -> -77612.523 | M18: ='Revenue Model'!O$4 -> Jun-27 | N18: ='Revenue Model'!O$9 -> 165.35135
A19: ='Revenue Model'!P$4 -> Jul-27 | B19: ='Revenue Model'!P$17 -> 91763.251 | C19: ='Revenue Model'!P$18 -> 1101159 | D19: ='P&L'!P$8 -> 88864.611 | F19: ='P&L'!P$4 -> Jul-27 | G19: ='P&L'!P$8 -> 88864.611 | H19: =COGS!P$11+Opex!P$22 -> 114432.42 | J19: ='Cash Runway'!P$4 -> Jul-27 | K19: ='Cash Runway'!P$19 -> -103180.33 | M19: ='Revenue Model'!P$4 -> Jul-27 | N19: ='Revenue Model'!P$9 -> 176.23026
A20: ='Revenue Model'!Q$4 -> Aug-27 | B20: ='Revenue Model'!Q$17 -> 97812.697 | C20: ='Revenue Model'!Q$18 -> 1173752.4 | D20: ='P&L'!Q$8 -> 94787.974 | F20: ='P&L'!Q$4 -> Aug-27 | G20: ='P&L'!Q$8 -> 94787.974 | H20: =COGS!Q$11+Opex!Q$22 -> 116858.35 | J20: ='Cash Runway'!Q$4 -> Aug-27 | K20: ='Cash Runway'!Q$19 -> -125250.71 | M20: ='Revenue Model'!Q$4 -> Aug-27 | N20: ='Revenue Model'!Q$9 -> 187.57478
A21: ='Revenue Model'!R$4 -> Sep-27 | B21: ='Revenue Model'!R$17 -> 104127.86 | C21: ='Revenue Model'!R$18 -> 1249534.4 | D21: ='P&L'!R$8 -> 100970.28 | F21: ='P&L'!R$4 -> Sep-27 | G21: ='P&L'!R$8 -> 100970.28 | H21: =COGS!R$11+Opex!R$22 -> 119390.49 | J21: ='Cash Runway'!R$4 -> Sep-27 | K21: ='Cash Runway'!R$19 -> -143670.92 | M21: ='Revenue Model'!R$4 -> Sep-27 | N21: ='Revenue Model'!R$9 -> 199.41053
A22: ='Revenue Model'!S$4 -> Oct-27 | B22: ='Revenue Model'!S$17 -> 110722.96 | C22: ='Revenue Model'!S$18 -> 1328675.5 | D22: ='P&L'!S$8 -> 107425.41 | F22: ='P&L'!S$4 -> Oct-27 | G22: ='P&L'!S$8 -> 107425.41 | H22: =COGS!S$11+Opex!S$22 -> 122034.28 | J22: ='Cash Runway'!S$4 -> Oct-27 | K22: ='Cash Runway'!S$19 -> -158279.79 | M22: ='Revenue Model'!S$4 -> Oct-27 | N22: ='Revenue Model'!S$9 -> 211.76436
A23: ='Revenue Model'!T$4 -> Nov-27 | B23: ='Revenue Model'!T$17 -> 117612.89 | C23: ='Revenue Model'!T$18 -> 1411354.7 | D23: ='P&L'!T$8 -> 114167.92 | F23: ='P&L'!T$4 -> Nov-27 | G23: ='P&L'!T$8 -> 114167.92 | H23: =COGS!T$11+Opex!T$22 -> 124795.45 | J23: ='Cash Runway'!T$4 -> Nov-27 | K23: ='Cash Runway'!T$19 -> -168907.31 | M23: ='Revenue Model'!T$4 -> Nov-27 | N23: ='Revenue Model'!T$9 -> 224.66438
A24: ='Revenue Model'!U$4 -> Dec-27 | B24: ='Revenue Model'!U$17 -> 124813.26 | C24: ='Revenue Model'!U$18 -> 1497759.2 | D24: ='P&L'!U$8 -> 121213.08 | F24: ='P&L'!U$4 -> Dec-27 | G24: ='P&L'!U$8 -> 121213.08 | H24: =COGS!U$11+Opex!U$22 -> 127679.98 | J24: ='Cash Runway'!U$4 -> Dec-27 | K24: ='Cash Runway'!U$19 -> -175374.22 | M24: ='Revenue Model'!U$4 -> Dec-27 | N24: ='Revenue Model'!U$9 -> 238.14005
A25: ='Revenue Model'!V$4 -> Jan-28 | B25: ='Revenue Model'!V$17 -> 132340.47 | C25: ='Revenue Model'!V$18 -> 1588085.6 | D25: ='P&L'!V$8 -> 128576.87 | F25: ='P&L'!V$4 -> Jan-28 | G25: ='P&L'!V$8 -> 128576.87 | H25: =COGS!V$11+Opex!V$22 -> 130694.17 | J25: ='Cash Runway'!V$4 -> Jan-28 | K25: ='Cash Runway'!V$19 -> -177491.52 | M25: ='Revenue Model'!V$4 -> Jan-28 | N25: ='Revenue Model'!V$9 -> 252.22223
A26: ='Revenue Model'!W$4 -> Feb-28 | B26: ='Revenue Model'!W$17 -> 140211.67 | C26: ='Revenue Model'!W$18 -> 1682540.1 | D26: ='P&L'!W$8 -> 136276.07 | F26: ='P&L'!W$4 -> Feb-28 | G26: ='P&L'!W$8 -> 136276.07 | H26: =COGS!W$11+Opex!W$22 -> 133844.61 | J26: ='Cash Runway'!W$4 -> Feb-28 | K26: ='Cash Runway'!W$19 -> -175060.06 | M26: ='Revenue Model'!W$4 -> Feb-28 | N26: ='Revenue Model'!W$9 -> 266.94327
A27: ='Revenue Model'!X$4 -> Mar-28 | B27: ='Revenue Model'!X$17 -> 148444.9 | C27: ='Revenue Model'!X$18 -> 1781338.8 | D27: ='P&L'!X$8 -> 144328.29 | F27: ='P&L'!X$4 -> Mar-28 | G27: ='P&L'!X$8 -> 144328.29 | H27: =COGS!X$11+Opex!X$22 -> 137138.21 | J27: ='Cash Runway'!X$4 -> Mar-28 | K27: ='Cash Runway'!X$19 -> -167869.99 | M27: ='Revenue Model'!X$4 -> Mar-28 | N27: ='Revenue Model'!X$9 -> 282.33705
A28: ='Revenue Model'!Y$4 -> Apr-28 | B28: ='Revenue Model'!Y$17 -> 157059.03 | C28: ='Revenue Model'!Y$18 -> 1884708.4 | D28: ='P&L'!Y$8 -> 152751.97 | F28: ='P&L'!Y$4 -> Apr-28 | G28: ='P&L'!Y$8 -> 152751.97 | H28: =COGS!Y$11+Opex!Y$22 -> 140582.26 | J28: ='Cash Runway'!Y$4 -> Apr-28 | K28: ='Cash Runway'!Y$19 -> -155700.28 | M28: ='Revenue Model'!Y$4 -> Apr-28 | N28: ='Revenue Model'!Y$9 -> 298.43913

Sheet Commentary
A1: Model Commentary
A3: Area | B3: Observation | C3: Why It Matters | D3: Suggested Action
A4: Revenue | B4: Growth is driven by new customers, churn, and small monthly expansion. | C4: This makes the model more realistic than manually entered revenue. | D4: Validate customer acquisition and churn with actual pipeline data.
A5: Gross Margin | B5: Gross margin is built from hosting, third-party COGS, payment processing, and implementation support. | C5: Investors will check whether margin assumptions are believable. | D5: Replace placeholder COGS rates with actual vendor data.
A6: Opex | B6: Opex is separated into payroll and non-payroll spend. | C6: This makes burn and runway easier to audit. | D6: Review hiring plan and CAC spend before using externally.
A7: Cash | B7: The model flags funding need when cash goes below the minimum threshold. | C7: Runway is usually the most important founder-level output. | D7: Add planned financing if a fundraise is expected.
A8: Dashboard | B8: Charts and KPI cards are separated from detailed model tabs. | C8: This prevents chart labels from overlapping the core calculations. | D8: Use the dashboard for presentation, and the model tabs for audit.

Sheet Board Analysis
A1: Cloud.AI Board Analysis
A2: Founder-friendly board review tied to the actual model outputs.
A4: 1. Executive Summary
A5: Growth | B5: ="ARR grows from "&TEXT('Revenue Model'!B18,"$#,##0")&" to "&TEXT('Revenue Model'!Y18,"$#,##0")&", with ending MRR of "&TEXT('Revenue Model'!Y17,"$#,##0")&" and "&TEXT('Revenue Model'!Y9,"0.0")&" ending customers. Growth is strong, but it relies on sustained new customer additions and controlled churn." -> ARR grows from $340,695 to $1,884,708, with ending MRR of $157,059 and 298.4 ending customers. Growth is strong, but it relies on sustained new customer additions and controlled churn.
A6: Profitability | B6: ="EBITDA improves from "&TEXT('P&L'!B22,"$#,##0;($#,##0)")&" to "&TEXT('P&L'!Y22,"$#,##0;($#,##0)")&", and EBITDA margin ends at "&TEXT('P&L'!Y23,"0.0%")&". The business moves toward profitability, but scale arrives after a meaningful cash drawdown." -> EBITDA improves from ($30,802) to $12,170, and EBITDA margin ends at 8.0%. The business moves toward profitability, but scale arrives after a meaningful cash drawdown.
A7: Cash runway | B7: ="Starting cash is "&TEXT('Cash Runway'!B6,"$#,##0")&" and ending cash is "&TEXT('Cash Runway'!Y19,"$#,##0;($#,##0)")&". Maximum modeled funding need is "&TEXT(MAX('Cash Runway'!B21:Y21),"$#,##0")&", so financing is the clearest board-level issue." -> Starting cash is $400,000 and ending cash is ($155,700). Maximum modeled funding need is $252,492, so financing is the clearest board-level issue.
A8: SaaS health | B8: ="Gross margin is "&TEXT('P&L'!Y13,"0.0%")&", NRR is "&TEXT('Revenue Model'!Y28,"0.0%")&", and LTV:CAC is "&TEXT('SaaS KPI Dashboard'!G10,"0.0x")&". Margins and unit economics look good, but NRR below 100% means expansion is not fully offsetting churn." -> Gross margin is 78.0%, NRR is 97.5%, and LTV:CAC is 10.8x. Margins and unit economics look good, but NRR below 100% means expansion is not fully offsetting churn.
A10: 2. Growth Analysis
A11: MRR / ARR | B11: ="MRR increases from "&TEXT('Revenue Model'!B17,"$#,##0")&" to "&TEXT('Revenue Model'!Y17,"$#,##0")&"; ARR increases from "&TEXT('Revenue Model'!B18,"$#,##0")&" to "&TEXT('Revenue Model'!Y18,"$#,##0")&". This is healthy recurring revenue growth." -> MRR increases from $28,391 to $157,059; ARR increases from $340,695 to $1,884,708. This is healthy recurring revenue growth.
A12: Customers | B12: ="Ending customers grow from "&TEXT('Revenue Model'!B9,"0.0")&" to "&TEXT('Revenue Model'!Y9,"0.0")&". The model assumes customer growth scales materially over the 24-month period." -> Ending customers grow from 56.5 to 298.4. The model assumes customer growth scales materially over the 24-month period.
A13: New customers | B13: ="New customers grow from "&TEXT('Revenue Model'!B7,"0.0")&" to "&TEXT('Revenue Model'!Y7,"0.0")&" per month, driven by "&TEXT(Assumptions!$C$17,"0.0%")&" monthly new-customer growth. This is achievable only if GTM capacity and CAC efficiency hold." -> New customers grow from 8.0 to 24.6 per month, driven by 5.0% monthly new-customer growth. This is achievable only if GTM capacity and CAC efficiency hold.
A14: Churn | B14: ="Customer churn is "&TEXT('Revenue Model'!Y24,"0.0%")&" monthly. Churned customers rise from "&TEXT('Revenue Model'!B8,"0.0")&" to "&TEXT('Revenue Model'!Y8,"0.0")&" as the base grows, which creates a rising retention burden." -> Customer churn is 3.0% monthly. Churned customers rise from 1.5 to 8.5 as the base grows, which creates a rising retention burden.
A15: Expansion / NRR | B15: ="NRR ends at "&TEXT('Revenue Model'!Y28,"0.0%")&" with monthly expansion / price uplift of "&TEXT(Assumptions!$C$19,"0.0%")&". The growth is good, but net retention should move above 100% for a healthier SaaS profile." -> NRR ends at 97.5% with monthly expansion / price uplift of 0.5%. The growth is good, but net retention should move above 100% for a healthier SaaS profile.
A17: 3. Profitability Analysis
A18: Gross margin | B18: ="Gross margin stays at "&TEXT('P&L'!Y13,"0.0%")&" and ties to the target of "&TEXT(Assumptions!$C$23,"0.0%")&". This is a strong SaaS margin profile." -> Gross margin stays at 78.0% and ties to the target of 78.0%. This is a strong SaaS margin profile.
A19: EBITDA | B19: ="EBITDA moves from "&TEXT('P&L'!B22,"$#,##0;($#,##0)")&" to "&TEXT('P&L'!Y22,"$#,##0;($#,##0)")&". The model moves toward profitability, but the company remains loss-making for much of the plan." -> EBITDA moves from ($30,802) to $12,170. The model moves toward profitability, but the company remains loss-making for much of the plan.
A20: Operating expenses | B20: ="Total opex grows from "&TEXT('P&L'!B19,"$#,##0")&" to "&TEXT('P&L'!Y19,"$#,##0")&" per month. Opex is the main driver of burn until revenue scale catches up." -> Total opex grows from $51,625 to $106,977 per month. Opex is the main driver of burn until revenue scale catches up.
A21: Cost areas | B21: ="Final-month opex mix is S&M "&TEXT('P&L'!Y16,"$#,##0")&", R&D "&TEXT('P&L'!Y17,"$#,##0")&", and G&A "&TEXT('P&L'!Y18,"$#,##0")&". Sales & Marketing is the largest cost area and should be tied to CAC payback and pipeline quality." -> Final-month opex mix is S&M $51,763, R&D $34,641, and G&A $20,572. Sales & Marketing is the largest cost area and should be tied to CAC payback and pipeline quality.
A22: Step costs | B22: ="G&A includes a one-time legal/compliance spend of "&TEXT(Assumptions!$C$40,"$#,##0")&" in month "&Assumptions!$C$39&". Board review should separate one-time costs from structural burn." -> G&A includes a one-time legal/compliance spend of $15,000 in month 12. Board review should separate one-time costs from structural burn.
A24: 4. Cash Runway Analysis
A25: Starting / ending cash | B25: ="Cash starts at "&TEXT('Cash Runway'!B6,"$#,##0")&" and ends at "&TEXT('Cash Runway'!Y19,"$#,##0;($#,##0)")&". The ending balance is negative without new funding." -> Cash starts at $400,000 and ends at ($155,700). The ending balance is negative without new funding.
A26: Monthly burn | B26: ="Net burn starts at "&TEXT('Cash Runway'!B18,"$#,##0")&" and peaks at "&TEXT(MAX('Cash Runway'!B18:Y18),"$#,##0")&". Burn improves later as revenue scales." -> Net burn starts at $30,802 and peaks at $48,515. Burn improves later as revenue scales.
A27: Runway timing | B27: {="Cash falls below the "&TEXT(Assumptions!$C$9,"$#,##0")&" minimum threshold in "&INDEX('Cash Runway'!B$4:Y$4,MATCH("Below Minimum",'Cash Runway'!B22:Y22,0))&" and turns negative in "&INDEX('Cash Runway'!B$4:Y$4,MATCH(TRUE,'Cash Runway'!B19:Y19<0,0))&". Funding should be addressed before that window."} -> Cash falls below the $75,000 minimum threshold in Feb-27 and turns negative in Apr-27. Funding should be addressed before that window.
A28: Funding need | B28: ="Maximum funding need to maintain minimum cash is "&TEXT(MAX('Cash Runway'!B21:Y21),"$#,##0")&". Management should raise more than the modeled shortfall to allow execution buffer." -> Maximum funding need to maintain minimum cash is $252,492. Management should raise more than the modeled shortfall to allow execution buffer.
A30: 5. SaaS KPI Analysis
A31: MRR / ARR | B31: ="Ending MRR is "&TEXT('SaaS KPI Dashboard'!D5,"$#,##0")&" and ending ARR is "&TEXT('SaaS KPI Dashboard'!A5,"$#,##0")&". This shows a scaled recurring revenue base by the end of the plan." -> Ending MRR is $157,059 and ending ARR is $1,884,708. This shows a scaled recurring revenue base by the end of the plan.
A32: Gross margin | B32: ="Gross margin is "&TEXT('SaaS KPI Dashboard'!A10,"0.0%")&". This supports attractive SaaS economics if COGS scale stays disciplined." -> Gross margin is 78.0%. This supports attractive SaaS economics if COGS scale stays disciplined.
A33: Churn / NRR | B33: ="Monthly churn is "&TEXT('Revenue Model'!Y24,"0.0%")&" and NRR is "&TEXT('Revenue Model'!Y28,"0.0%")&". Retention is the key SaaS health risk because NRR is below 100%." -> Monthly churn is 3.0% and NRR is 97.5%. Retention is the key SaaS health risk because NRR is below 100%.
A34: CAC payback | B34: ="CAC payback is approximately "&TEXT(Assumptions!$C$35/(Assumptions!$C$14*'P&L'!Y13),"0.0")&" months using CAC per customer and gross profit per customer. This is attractive if CAC includes the full sales effort." -> CAC payback is approximately 3.1 months using CAC per customer and gross profit per customer. This is attractive if CAC includes the full sales effort.
A35: LTV:CAC | B35: ="LTV:CAC is "&TEXT('SaaS KPI Dashboard'!G10,"0.0x")&". Unit economics look strong, but the board should confirm CAC is fully loaded." -> LTV:CAC is 10.8x. Unit economics look strong, but the board should confirm CAC is fully loaded.
A36: Burn multiple | B36: =IF('Cash Runway'!Y18<=0,"Final month is cash-generative, so current burn multiple is not meaningful. The board should instead focus on bridging the cash trough.","Final burn multiple is "&TEXT('Cash Runway'!Y18/('Revenue Model'!Y26*12),"0.0x")) -> Final month is cash-generative, so current burn multiple is not meaningful. The board should instead focus on bridging the cash trough.
A37: Rule of 40 | B37: ="Forecast Rule of 40 is approximately "&TEXT(('Revenue Model'!Y18/'Revenue Model'!B18)^(12/23)-1+'P&L'!Y23,"0.0%")&" using ARR CAGR plus final EBITDA margin. Growth is strong, but cash runway still needs board focus." -> Forecast Rule of 40 is approximately 152.1% using ARR CAGR plus final EBITDA margin. Growth is strong, but cash runway still needs board focus.
A39: 6. Scenario Analysis
A40: Conservative | B40: ="Conservative case: "&TEXT('Scenario Analysis'!B4,"0.0%")&" new customer growth, "&TEXT('Scenario Analysis'!C4,"0.0%")&" churn, ending ARR "&TEXT('Scenario Analysis'!E4,"$#,##0")&", ending cash "&TEXT('Scenario Analysis'!F4,"$#,##0;($#,##0)")&", funding need "&TEXT('Scenario Analysis'!G4,"$#,##0")&". Slower acquisition and higher churn materially worsen liquidity." -> Conservative case: 2.0% new customer growth, 4.0% churn, ending ARR $1,209,983, ending cash ($358,118), funding need $433,118. Slower acquisition and higher churn materially worsen liquidity.
A41: Base case | B41: ="Base case: "&TEXT('Scenario Analysis'!B5,"0.0%")&" new customer growth, "&TEXT('Scenario Analysis'!C5,"0.0%")&" churn, ending ARR "&TEXT('Scenario Analysis'!E5,"$#,##0")&", ending cash "&TEXT('Scenario Analysis'!F5,"$#,##0;($#,##0)")&", funding need "&TEXT('Scenario Analysis'!G5,"$#,##0")&". This is the most realistic case because it matches the core model." -> Base case: 5.0% new customer growth, 3.0% churn, ending ARR $1,884,708, ending cash ($155,700), funding need $230,700. This is the most realistic case because it matches the core model.
A42: Optimistic | B42: ="Optimistic case: "&TEXT('Scenario Analysis'!B6,"0.0%")&" new customer growth, "&TEXT('Scenario Analysis'!C6,"0.0%")&" churn, ending ARR "&TEXT('Scenario Analysis'!E6,"$#,##0")&", ending cash "&TEXT('Scenario Analysis'!F6,"$#,##0;($#,##0)")&", funding need "&TEXT('Scenario Analysis'!G6,"$#,##0")&". Upside nearly solves the cash gap, but requires acquisition and churn to both outperform." -> Optimistic case: 8.0% new customer growth, 2.0% churn, ending ARR $2,559,434, ending cash $46,717, funding need $28,283. Upside nearly solves the cash gap, but requires acquisition and churn to both outperform.
A43: Board view | B43: Use the base case for operating decisions, but size financing against the conservative case because the cash gap is sensitive to acquisition and churn.
A45: 7. Key Risks
A46: RED | B46: Liquidity / funding timing
A47: AMBER | B47: NRR below 100%
A48: AMBER | B48: Churn scales with base
A49: AMBER | B49: Opex / hiring pace
A50: GREEN | B50: Gross margin quality
A51: AMBER | B51: Scenario dependence
A53: 8. Recommended Actions
A54: 1 | B54: Start fundraising preparation now and size the raise above the modeled maximum funding need.
A55: 2 | B55: Review hiring and discretionary opex before the burn peak; gate spend to cash milestones.
A56: 3 | B56: Create a retention and expansion plan to push NRR above 100%.
A57: 4 | B57: Tie paid acquisition budget to CAC payback, pipeline conversion, and churn by cohort.
A58: 5 | B58: Create a monthly board KPI pack tracking ARR, NRR, burn, runway, and scenario movement.
A60: 9. Board Discussion Points
A61: 1 | B61: Should we raise before cash drops below the minimum threshold, and how much buffer should we add?
A62: 2 | B62: What actions will move NRR from below 100% to expansion-led growth?
A63: 3 | B63: Can GTM sustain 5% monthly growth in new customer additions without CAC deterioration?
A64: 4 | B64: Which opex commitments can be delayed or gated until cash position improves?
A65: 5 | B65: Should the base case or conservative case drive the financing plan?

Sheet Board Deck Input
A1: Slide No | B1: Slide Title | C1: Key Message | D1: Supporting Metrics | E1: Chart Reference | F1: Speaker Notes
A2: 1 | B2: Executive Summary | C2: =_xlfn.TEXTJOIN(" ",TRUE,"ARR scales from "&TEXT('Revenue Model'!B18,"$#,##0")&" to "&TEXT('Revenue Model'!Y18,"$#,##0")&", while ending cash falls to "&TEXT('Cash Runway'!Y19,"$#,##0;($#,##0)")&".","Decision: prioritize financing timing while protecting growth quality.") -> ARR scales from $340,695 to $1,884,708, while ending cash falls to ($155,700). Decision: prioritize financing timing while protecting growth quality. | D2: =_xlfn.TEXTJOIN(" | ",TRUE,"Ending ARR: "&TEXT('SaaS KPI Dashboard'!A5,"$#,##0"),"Ending MRR: "&TEXT('SaaS KPI Dashboard'!D5,"$#,##0"),"Ending customers: "&TEXT('SaaS KPI Dashboard'!G5,"0.0"),"Funding need: "&TEXT('SaaS KPI Dashboard'!J10,"$#,##0")) -> Ending ARR: $1,884,708 | Ending MRR: $157,059 | Ending customers: 298.4 | Funding need: $252,492 | E2: Charts sheet: ARR / MRR growth chart fed by Charts!A4:D28, plus KPI dashboard tiles. | F2: =_xlfn.TEXTJOIN(" ",TRUE,"Open with the trade-off: growth is working, but liquidity is not yet self-funded.","Use the board ask to align on raise timing before cash moves below the minimum threshold and turns negative.") -> Open with the trade-off: growth is working, but liquidity is not yet self-funded. Use the board ask to align on raise timing before cash moves below the minimum threshold and turns negative.
A3: 2 | B3: Revenue Growth | C3: =_xlfn.TEXTJOIN(" ",TRUE,"Recurring revenue grows materially: MRR moves from "&TEXT('Revenue Model'!B17,"$#,##0")&" to "&TEXT('Revenue Model'!Y17,"$#,##0")&" and ARR reaches "&TEXT('Revenue Model'!Y18,"$#,##0")&".","Decision: validate GTM capacity behind the growth curve.") -> Recurring revenue grows materially: MRR moves from $28,391 to $157,059 and ARR reaches $1,884,708. Decision: validate GTM capacity behind the growth curve. | D3: =_xlfn.TEXTJOIN(" | ",TRUE,"MRR: "&TEXT('Revenue Model'!B17,"$#,##0")&" → "&TEXT('Revenue Model'!Y17,"$#,##0"),"ARR: "&TEXT('Revenue Model'!B18,"$#,##0")&" → "&TEXT('Revenue Model'!Y18,"$#,##0"),"New customers / month: "&TEXT('Revenue Model'!B7,"0.0")&" → "&TEXT('Revenue Model'!Y7,"0.0")) -> MRR: $28,391 → $157,059 | ARR: $340,695 → $1,884,708 | New customers / month: 8.0 → 24.6 | E3: Charts sheet: ARR / MRR / revenue trend chart fed by Charts!A4:D28. | F3: =_xlfn.TEXTJOIN(" ",TRUE,"Emphasize that growth comes from sustained new customer additions, not one-off services revenue.","Ask whether sales capacity, pipeline conversion, and CAC controls support the 5.0% monthly new-customer growth assumption.") -> Emphasize that growth comes from sustained new customer additions, not one-off services revenue. Ask whether sales capacity, pipeline conversion, and CAC controls support the 5.0% monthly new-customer growth assumption.
A4: 3 | B4: Customer Growth & Churn | C4: =_xlfn.TEXTJOIN(" ",TRUE,"Customers grow from "&TEXT('Revenue Model'!B9,"0.0")&" to "&TEXT('Revenue Model'!Y9,"0.0")&", but churned customers rise with the base.","Decision: make retention a board-level operating priority.") -> Customers grow from 56.5 to 298.4, but churned customers rise with the base. Decision: make retention a board-level operating priority. | D4: =_xlfn.TEXTJOIN(" | ",TRUE,"Ending customers: "&TEXT('Revenue Model'!B9,"0.0")&" → "&TEXT('Revenue Model'!Y9,"0.0"),"Monthly churn: "&TEXT('Revenue Model'!Y24,"0.0%"),"Churned customers: "&TEXT('Revenue Model'!B8,"0.0")&" → "&TEXT('Revenue Model'!Y8,"0.0"),"NRR: "&TEXT('Revenue Model'!Y28,"0.0%")) -> Ending customers: 56.5 → 298.4 | Monthly churn: 3.0% | Churned customers: 1.5 → 8.5 | NRR: 97.5% | E4: Charts sheet: Ending customer trend chart fed by Charts!M4:N28. | F4: =_xlfn.TEXTJOIN(" ",TRUE,"Frame this as the operating constraint behind growth quality.","NRR below 100% means expansion is not yet fully offsetting churn, so retention and upsell motions need explicit ownership.") -> Frame this as the operating constraint behind growth quality. NRR below 100% means expansion is not yet fully offsetting churn, so retention and upsell motions need explicit ownership.
A5: 4 | B5: Profitability Trend | C5: =_xlfn.TEXTJOIN(" ",TRUE,"EBITDA improves from "&TEXT('P&L'!B22,"$#,##0;($#,##0)")&" to "&TEXT('P&L'!Y22,"$#,##0;($#,##0)")&" and reaches a "&TEXT('P&L'!Y23,"0.0%")&" margin.","Decision: gate opex to the cash trough while preserving revenue capacity.") -> EBITDA improves from ($30,802) to $12,170 and reaches a 8.0% margin. Decision: gate opex to the cash trough while preserving revenue capacity. | D5: =_xlfn.TEXTJOIN(" | ",TRUE,"Revenue: "&TEXT('P&L'!B8,"$#,##0")&" → "&TEXT('P&L'!Y8,"$#,##0"),"Gross margin: "&TEXT('P&L'!Y13,"0.0%"),"EBITDA: "&TEXT('P&L'!B22,"$#,##0;($#,##0)")&" → "&TEXT('P&L'!Y22,"$#,##0;($#,##0)"),"Total opex: "&TEXT('P&L'!B19,"$#,##0")&" → "&TEXT('P&L'!Y19,"$#,##0")) -> Revenue: $26,696 → $152,752 | Gross margin: 78.0% | EBITDA: ($30,802) → $12,170 | Total opex: $51,625 → $106,977 | E5: Charts sheet: Revenue vs total expenses chart fed by Charts!F4:H28. | F5: =_xlfn.TEXTJOIN(" ",TRUE,"Show that margin expansion is real, but it arrives after a long loss-making period.","Call out Sales & Marketing as the largest final-month opex bucket and tie spend approval to CAC payback and pipeline quality.") -> Show that margin expansion is real, but it arrives after a long loss-making period. Call out Sales & Marketing as the largest final-month opex bucket and tie spend approval to CAC payback and pipeline quality.
A6: 5 | B6: Cash Runway | C6: {=_xlfn.TEXTJOIN(" ",TRUE,"Cash falls below the "&TEXT(Assumptions!$C$9,"$#,##0")&" minimum in "&INDEX('Cash Runway'!B$4:Y$4,MATCH("Below Minimum",'Cash Runway'!B22:Y22,0))&" and turns negative in "&INDEX('Cash Runway'!B$4:Y$4,MATCH(TRUE,'Cash Runway'!B19:Y19<0,0))&".","Decision: begin financing work before the risk window.")} -> Cash falls below the $75,000 minimum in Feb-27 and turns negative in Apr-27. Decision: begin financing work before the risk window. | D6: =_xlfn.TEXTJOIN(" | ",TRUE,"Starting cash: "&TEXT('Cash Runway'!B6,"$#,##0"),"Ending cash: "&TEXT('Cash Runway'!Y19,"$#,##0;($#,##0)"),"Peak net burn: "&TEXT(MAX('Cash Runway'!B18:Y18),"$#,##0"),"Max funding need: "&TEXT(MAX('Cash Runway'!B21:Y21),"$#,##0")) -> Starting cash: $400,000 | Ending cash: ($155,700) | Peak net burn: $48,515 | Max funding need: $252,492 | E6: Charts sheet: Ending cash runway chart fed by Charts!J4:K28. | F6: =_xlfn.TEXTJOIN(" ",TRUE,"This is the clearest board decision slide.","Recommend sizing the financing above the modeled funding need because the model shows negative ending cash even as EBITDA turns positive late in the plan.") -> This is the clearest board decision slide. Recommend sizing the financing above the modeled funding need because the model shows negative ending cash even as EBITDA turns positive late in the plan.
A7: 6 | B7: SaaS KPI Review | C7: =_xlfn.TEXTJOIN(" ",TRUE,"The model shows strong SaaS economics with "&TEXT('P&L'!Y13,"0.0%")&" gross margin and "&TEXT('SaaS KPI Dashboard'!G10,"0.0x")&" LTV:CAC, but NRR is only "&TEXT('Revenue Model'!Y28,"0.0%")&".","Decision: confirm CAC is fully loaded and raise retention ambition.") -> The model shows strong SaaS economics with 78.0% gross margin and 10.8x LTV:CAC, but NRR is only 97.5%. Decision: confirm CAC is fully loaded and raise retention ambition. | D7: =_xlfn.TEXTJOIN(" | ",TRUE,"Gross margin: "&TEXT('SaaS KPI Dashboard'!A10,"0.0%"),"EBITDA margin: "&TEXT('SaaS KPI Dashboard'!D10,"0.0%"),"LTV:CAC: "&TEXT('SaaS KPI Dashboard'!G10,"0.0x"),"NRR: "&TEXT('Revenue Model'!Y28,"0.0%")) -> Gross margin: 78.0% | EBITDA margin: 8.0% | LTV:CAC: 10.8x | NRR: 97.5% | E7: SaaS KPI Dashboard: summary tiles A4:J11 and takeaway block A14:B18. | F7: =_xlfn.TEXTJOIN(" ",TRUE,"Position the KPI story as attractive but not yet fully de-risked.","The board should pressure-test CAC definition and approve a retention/expansion plan to move NRR above 100%.") -> Position the KPI story as attractive but not yet fully de-risked. The board should pressure-test CAC definition and approve a retention/expansion plan to move NRR above 100%.
A8: 7 | B8: Scenario Analysis | C8: =_xlfn.TEXTJOIN(" ",TRUE,"Liquidity is highly sensitive to acquisition and churn: conservative funding need is "&TEXT('Scenario Analysis'!G4,"$#,##0")&" versus "&TEXT('Scenario Analysis'!G5,"$#,##0")&" in base and "&TEXT('Scenario Analysis'!G6,"$#,##0")&" in upside.","Decision: finance against downside, operate against base.") -> Liquidity is highly sensitive to acquisition and churn: conservative funding need is $433,118 versus $230,700 in base and $28,283 in upside. Decision: finance against downside, operate against base. | D8: =_xlfn.TEXTJOIN(" | ",TRUE,"Conservative ARR / cash: "&TEXT('Scenario Analysis'!E4,"$#,##0")&" / "&TEXT('Scenario Analysis'!F4,"$#,##0;($#,##0)"),"Base ARR / cash: "&TEXT('Scenario Analysis'!E5,"$#,##0")&" / "&TEXT('Scenario Analysis'!F5,"$#,##0;($#,##0)"),"Optimistic ARR / cash: "&TEXT('Scenario Analysis'!E6,"$#,##0")&" / "&TEXT('Scenario Analysis'!F6,"$#,##0;($#,##0)")) -> Conservative ARR / cash: $1,209,983 / ($358,118) | Base ARR / cash: $1,884,708 / ($155,700) | Optimistic ARR / cash: $2,559,434 / $46,717 | E8: Scenario Analysis sheet: scenario comparison table A3:H6. | F8: =_xlfn.TEXTJOIN(" ",TRUE,"Use this slide to separate operating plan from financing plan.","Base case should guide execution; conservative case should guide capital buffer because liquidity deteriorates quickly when acquisition slows and churn rises.") -> Use this slide to separate operating plan from financing plan. Base case should guide execution; conservative case should guide capital buffer because liquidity deteriorates quickly when acquisition slows and churn rises.
A9: 8 | B9: Key Risks | C9: =_xlfn.TEXTJOIN(" ",TRUE,"The main risk is liquidity timing, followed by NRR below 100%, churn scaling with the customer base, and opex commitments before cash improves.","Decision: assign owners to financing, retention, and spend gates.") -> The main risk is liquidity timing, followed by NRR below 100%, churn scaling with the customer base, and opex commitments before cash improves. Decision: assign owners to financing, retention, and spend gates. | D9: =_xlfn.TEXTJOIN(" | ",TRUE,"Ending cash: "&TEXT('Cash Runway'!Y19,"$#,##0;($#,##0)"),"Max funding need: "&TEXT(MAX('Cash Runway'!B21:Y21),"$#,##0"),"NRR: "&TEXT('Revenue Model'!Y28,"0.0%"),"Total opex: "&TEXT('P&L'!B19,"$#,##0")&" → "&TEXT('P&L'!Y19,"$#,##0")) -> Ending cash: ($155,700) | Max funding need: $252,492 | NRR: 97.5% | Total opex: $51,625 → $106,977 | E9: Charts sheet: Ending cash runway chart fed by Charts!J4:K28, with risk list from Board Analysis A45:B51. | F9: =_xlfn.TEXTJOIN(" ",TRUE,"Avoid a generic risk list; keep this tied to the model’s cash and retention outputs.","Make the board discussion practical: who owns funding timing, NRR improvement, churn mitigation, and opex gating?") -> Avoid a generic risk list; keep this tied to the model’s cash and retention outputs. Make the board discussion practical: who owns funding timing, NRR improvement, churn mitigation, and opex gating?
A10: 9 | B10: Recommended Actions | C10: =_xlfn.TEXTJOIN(" ",TRUE,"Management should start fundraising preparation, gate opex before the burn peak, and build a retention/expansion plan to move NRR above 100%.","Decision: approve the operating guardrails for the next board cycle.") -> Management should start fundraising preparation, gate opex before the burn peak, and build a retention/expansion plan to move NRR above 100%. Decision: approve the operating guardrails for the next board cycle. | D10: =_xlfn.TEXTJOIN(" | ",TRUE,"Cash below minimum: "&INDEX('Cash Runway'!B$4:Y$4,MATCH("Below Minimum",'Cash Runway'!B22:Y22,0)),"Peak burn: "&TEXT(MAX('Cash Runway'!B18:Y18),"$#,##0"),"Funding need: "&TEXT(MAX('Cash Runway'!B21:Y21),"$#,##0"),"NRR: "&TEXT('Revenue Model'!Y28,"0.0%")) -> Cash below minimum: Feb-27 | Peak burn: $48,515 | Funding need: $252,492 | NRR: 97.5% | E10: Scenario Analysis table A3:H6 plus Cash Runway chart fed by Charts!J4:K28. | F10: =_xlfn.TEXTJOIN(" ",TRUE,"Keep this slide action-oriented: financing timeline, opex gates, retention plan, and CAC governance.","Ask for board alignment on the raise buffer and which spend commitments can be delayed if the conservative case develops.") -> Keep this slide action-oriented: financing timeline, opex gates, retention plan, and CAC governance. Ask for board alignment on the raise buffer and which spend commitments can be delayed if the conservative case develops.
A11: 10 | B11: Board Discussion Questions | C11: =_xlfn.TEXTJOIN(" ",TRUE,"The board needs decisions on raise timing and buffer, retention targets, GTM scalability, opex flexibility, and whether conservative or base case drives financing.","Decision: convert discussion into owners and timing.") -> The board needs decisions on raise timing and buffer, retention targets, GTM scalability, opex flexibility, and whether conservative or base case drives financing. Decision: convert discussion into owners and timing. | D11: =_xlfn.TEXTJOIN(" | ",TRUE,"Raise trigger: "&INDEX('Cash Runway'!B$4:Y$4,MATCH("Below Minimum",'Cash Runway'!B22:Y22,0)),"Base funding need: "&TEXT('Scenario Analysis'!G5,"$#,##0"),"Conservative funding need: "&TEXT('Scenario Analysis'!G4,"$#,##0"),"New-customer growth: "&TEXT(Assumptions!$C$17,"0.0%")) -> Raise trigger: Feb-27 | Base funding need: $230,700 | Conservative funding need: $433,118 | New-customer growth: 5.0% | E11: Scenario Analysis table A3:H6 and Cash Runway chart fed by Charts!J4:K28. | F11: =_xlfn.TEXTJOIN(" ",TRUE,"End with explicit asks, not open-ended commentary.","Secure agreement on financing case, NRR target, GTM proof points, and cost gates before the next monthly review.") -> End with explicit asks, not open-ended commentary. Secure agreement on financing case, NRR target, GTM proof points, and cost gates before the next monthly review.
